Workbook

Sheet Tabla de Inversion
E9: MOB Y EQUIPO | F9: 83025
E10: EQUIPO DE COMPUTO | F10: 3000
E11: ENSERES | F11: 12732
E12: EQ. OFICINA | F12: 8089

Sheet VENTAS
A2: 2020
A3: CONCEPTO | B3: COSTO | C3: PERSONAL REQUERIDO | D3: ENERO | E3: FEBRERO | F3: MARZO | G3: ABRIL | H3: MAYO | I3: JUNIO | J3: JULIO | K3: AGOSTO | L3: SEPTIEMBRE | M3: OCTUBRE | N3: NOVIEMBRE | O3: DICIEMBRE | P3: TOTAL
A4: MANICURE | B4: 150 | C4: 4 | D4: =15*C4*B4 -> 9000 | E4: =20*C4*B4 -> 12000 | F4: =20*C4*B4 -> 12000 | G4: =10*C4*B4 -> 6000 | H4: =18*C4*B4 -> 10800 | I4: =8*C4*B4 -> 4800 | J4: =19*C4*B4 -> 11400 | K4: =15*C4*B4 -> 9000 | L4: =20*C4*B4 -> 12000 | M4: =15*C4*B4 -> 9000 | N4: =15*C4*B4 -> 9000 | O4: =16*C4*B4 -> 9600 | P4: =SUM(D4:O4) -> 114600
A5: PEDICURE | B5: 200 | C5: 4 | D5: =5*$C$5*$B$5 -> 4000 | E5: =20*$C$5*$B$5 -> 16000 | F5: =18*$C$5*$B$5 -> 14400 | G5: =12*$C$5*$B$5 -> 9600 | H5: =3*$C$5*$B$5 -> 2400 | I5: =3*$C$5*$B$5 -> 2400 | J5: =5*$C$5*$B$5 -> 4000 | K5: =8*$C$5*$B$5 -> 6400 | L5: =8*$C$5*$B$5 -> 6400 | M5: =5*$C$5*$B$5 -> 4000 | N5: =5*$C$5*$B$5 -> 4000 | O5: =5*$C$5*$B$5 -> 4000 | P5: =SUM(D5:O5) -> 77600
A6: FACIALES | B6: 300 | C6: 4 | D6: =2*$C$6*$B$6 -> 2400 | E6: =2*$C$6*$B$6 -> 2400 | F6: =3*$C$6*$B$6 -> 3600 | G6: =3*$C$6*$B$6 -> 3600 | H6: =1*$C$6*$B$6 -> 1200 | I6: =1*$C$6*$B$6 -> 1200 | J6: =1*$C$6*$B$6 -> 1200 | K6: =2*$C$6*$B$6 -> 2400 | L6: =6*$C$6*$B$6 -> 7200 | M6: =7*$C$6*$B$6 -> 8400 | N6: =3*$C$6*$B$6 -> 3600 | O6: =3*$C$6*$B$6 -> 3600 | P6: =SUM(D6:O6) -> 40800
A7: DEPILACIONES | B7: 200 | C7: 1 | D7: =65*$C$7*$B$7 -> 13000 | E7: =80*$C$7*$B$7 -> 16000 | F7: =70*$C$7*$B$7 -> 14000 | G7: =75*$C$7*$B$7 -> 15000 | H7: =80*$C$7*$B$7 -> 16000 | I7: =74*$C$7*$B$7 -> 14800 | J7: =30*$C$7*$B$7 -> 6000 | K7: =72*$C$7*$B$7 -> 14400 | L7: =100*$C$7*$B$7 -> 20000 | M7: =100*$C$7*$B$7 -> 20000 | N7: =90*$C$7*$B$7 -> 18000 | O7: =90*$C$7*$B$7 -> 18000 | P7: =SUM(D7:O7) -> 185200
A8: APAR. 50% (CONTADO) | B8: 1600 | C8: 1 | D8: =3*$C$8*$B$8 -> 4800 | E8: =3*$C$8*$B$8 -> 4800 | F8: =5*$C$8*$B$8 -> 8000 | G8: =7*$C$8*$B$8 -> 11200 | H8: =8*$C$8*$B$8 -> 12800 | I8: =4*$C$8*$B$8 -> 6400 | J8: =3*$C$8*$B$8 -> 4800 | K8: =4*$C$8*$B$8 -> 6400 | L8: =6*$C$8*$B$8 -> 9600 | M8: =5*$C$8*$B$8 -> 8000 | N8: =4*$C$8*$B$8 -> 6400 | O8: =4*$C$8*$B$8 -> 6400 | P8: =SUM(D8:O8) -> 89600
A9: APAR. 50% (15 DÍAS) | B9: 1600 | C9: 1 | D9: 0 | E9: =D8 -> 4800 | F9: =E8 -> 4800 | G9: =F8 -> 8000 | H9: =G8 -> 11200 | I9: =H8 -> 12800 | J9: =I8 -> 6400 | K9: =J8 -> 4800 | L9: =K8 -> 6400 | ... O9: =N8 -> 6400 | P9: =SUM(D9:O9) -> 83200
A10: SESIONES APARTO. | B10: 350 | C10: 1 | D10: =20*$C$10*$B$10 -> 7000 | E10: =13*$C$10*$B$10 -> 4550 | F10: =10*$C$10*$B$10 -> 3500 | G10: =0*$C$10*$B$10 -> 0 | H10: =0*$C$10*$B$10 -> 0 | I10: =4*$C$10*$B$10 -> 1400 | J10: =5*$C$10*$B$10 -> 1750 | K10: =8*$C$10*$B$10 -> 2800 | L10: =0*$C$10*$B$10 -> 0 | M10: =8*$C$10*$B$10 -> 2800 | N10: =0*$C$10*$B$10 -> 0 | O10: =12*$C$10*$B$10 -> 4200 | P10: =SUM(D10:O10) -> 28000
A11: RADIO FACIAL | B11: 250 | C11: 1 | D11: =4*$C$11*$B$11 -> 1000 | E11: =16*$C$11*$B$11 -> 4000 | F11: =40*$C$11*$B$11 -> 10000 | G11: =28*$C$11*$B$11 -> 7000 | H11: =22*$C$11*$B$11 -> 5500 | I11: =24*$C$11*$B$11 -> 6000 | J11: =50*$C$11*$B$11 -> 12500 | K11: =60*$C$11*$B$11 -> 15000 | L11: =25*$C$11*$B$11 -> 6250 | M11: =24*$C$11*$B$11 -> 6000 | N11: =24*$C$11*$B$11 -> 6000 | O11: =50*$C$11*$B$11 -> 12500 | P11: =SUM(D11:O11) -> 91750
A12: MASAJES | B12: 500 | C12: 1 | D12: =8*$C$12*$B$12 -> 4000 | E12: =13*$C$12*$B$12 -> 6500 | F12: =15*$C$12*$B$12 -> 7500 | G12: =4*$C$12*$B$12 -> 2000 | H12: =16*$C$12*$B$12 -> 8000 | I12: =5*$C$12*$B$12 -> 2500 | J12: =8*$C$12*$B$12 -> 4000 | K12: =6*$C$12*$B$12 -> 3000 | L12: =13*$C$12*$B$12 -> 6500 | M12: =9*$C$12*$B$12 -> 4500 | N12: =28*$C$12*$B$12 -> 14000 | O12: =10*$C$12*$B$12 -> 5000 | P12: =SUM(D12:O12) -> 67500
A13: PTO ENTRADAS | D13: =D4+D5+D6+D7+D8+D10+D11+D12+D9 -> 45200 | E13: =E4+E5+E6+E7+E8+E10+E11+E12+E9 -> 71050 | F13: =F4+F5+F6+F7+F8+F10+F11+F12+F9 -> 77800 | G13: =G4+G5+G6+G7+G8+G10+G11+G12+G9 -> 62400 | H13: =H4+H5+H6+H7+H8+H10+H11+H12+H9 -> 67900 | I13: =I4+I5+I6+I7+I8+I10+I11+I12+I9 -> 52300 | J13: =J4+J5+J6+J7+J8+J10+J11+J12+J9 -> 52050 | K13: =K4+K5+K6+K7+K8+K10+K11+K12+K9 -> 64200 | ... O13: =O4+O5+O6+O7+O8+O10+O11+O12+O9 -> 69700 | P13: =SUM(D13:O13) -> 778250
A14: VENTAS | D14: =D4+D5+D6+D7+D8+E9+D10+D11+D12 -> 50000 | E14: =E4+E5+E6+E7+E8+F9+E10+E11+E12 -> 71050 | F14: =F4+F5+F6+F7+F8+G9+F10+F11+F12 -> 81000 | G14: =G4+G5+G6+G7+G8+H9+G10+G11+G12 -> 65600 | H14: =H4+H5+H6+H7+H8+I9+H10+H11+H12 -> 69500 | I14: =I4+I5+I6+I7+I8+J9+I10+I11+I12 -> 45900 | J14: =J4+J5+J6+J7+J8+K9+J10+J11+J12 -> 50450 | K14: =K4+K5+K6+K7+K8+L9+K10+K11+K12 -> 65800 | ... N14: =N4+N5+N6+N7+N8+O9+N10+N11+N12 -> 67400 | O14: =O4+O5+O6+O7+O8+D27+O10+O11+O12 -> 69700 | P14: =SUM(D14:O14) -> 784650
A16: VENTAS INFLACIÓN | D16: =D14*1.05 -> 52500 | E16: =E14*1.05 -> 74602.5 | F16: =F14*1.05 -> 85050 | G16: =G14*1.05 -> 68880 | H16: =H14*1.05 -> 72975 | I16: =I14*1.05 -> 48195 | J16: =J14*1.05 -> 52972.5 | K16: =K14*1.05 -> 69090 | ... O16: =O14*1.05 -> 73185 | P16: =SUM(D16:O16) -> 823882.5
A17: AUMENTO 10% | D17: =D16*1.1 -> 57750 | E17: =E16*1.1 -> 82062.75 | F17: =F16*1.1 -> 93555 | G17: =G16*1.1 -> 75768 | H17: =H16*1.1 -> 80272.5 | I17: =I16*1.1 -> 53014.5 | J17: =J16*1.1 -> 58269.75 | K17: =K16*1.1 -> 75999 | ... O17: =O16*1.1 -> 80503.5 | P17: =SUM(D17:O17) -> 906270.75
A20: 2021
A21: CONCEPTO | B21: COSTO | C21: PERSONAL REQUERIDO | D21: ENERO | E21: FEBRERO | F21: MARZO | G21: ABRIL | H21: MAYO | I21: JUNIO | J21: JULIO | K21: AGOSTO | L21: SEPTIEMBRE | M21: OCTUBRE | N21: NOVIEMBRE | O21: DICIEMBRE | P21: TOTAL
A22: MANICURE | B22: 157.5 | C22: 1 | D22: =32*$C$22*$B$22 -> 5040 | E22: =40*$C$22*$B$22 -> 6300 | F22: =60*$C$22*$B$22 -> 9450 | G22: =40*$C$22*$B$22 -> 6300 | H22: =60*$C$22*$B$22 -> 9450 | I22: =60*$C$22*$B$22 -> 9450 | J22: =40*$C$22*$B$22 -> 6300 | K22: =45*$C$22*$B$22 -> 7087.5 | L22: =50*$C$22*$B$22 -> 7875 | M22: =50*$C$22*$B$22 -> 7875 | N22: =50*$C$22*$B$22 -> 7875 | O22: =70*$C$22*$B$22 -> 11025 | P22: =SUM(D22:O22) -> 94027.5
A23: PEDICURE | B23: 210 | C23: 1 | D23: =13*$C$23*$B$23 -> 2730 | E23: =12*$C$23*$B$23 -> 2520 | F23: =33*$C$23*$B$23 -> 6930 | G23: =40*$C$23*$B$23 -> 8400 | H23: =40*$C$23*$B$23 -> 8400 | I23: =8*$C$23*$B$23 -> 1680 | J23: =25*$C$23*$B$23 -> 5250 | K23: =20*$C$23*$B$23 -> 4200 | L23: =35*$C$23*$B$23 -> 7350 | M23: =15*$C$23*$B$23 -> 3150 | N23: =50*$C$23*$B$23 -> 10500 | O23: =45*$C$23*$B$23 -> 9450 | P23: =SUM(D23:O23) -> 70560
A24: FACIALES | B24: 315 | C24: 1 | D24: =8*$C$24*$B$24 -> 2520 | E24: =9*$C$24*$B$24 -> 2835 | F24: =18*$C$24*$B$24 -> 5670 | G24: =16*$C$24*$B$24 -> 5040 | H24: =18*$C$24*$B$24 -> 5670 | I24: =4*$C$24*$B$24 -> 1260 | J24: =20*$C$24*$B$24 -> 6300 | K24: =30*$C$24*$B$24 -> 9450 | L24: =18*$C$24*$B$24 -> 5670 | M24: =15*$C$24*$B$24 -> 4725 | N24: =30*$C$24*$B$24 -> 9450 | O24: =30*$C$24*$B$24 -> 9450 | P24: =SUM(D24:O24) -> 68040
A25: DEPILACIONES | B25: 210 | C25: 1 | D25: =80*$C$25*$B$25 -> 16800 | E25: =90*$C$25*$B$25 -> 18900 | F25: =100*$C$25*$B$25 -> 21000 | G25: =70*$C$25*$B$25 -> 14700 | H25: =85*$C$25*$B$25 -> 17850 | I25: =70*$C$25*$B$25 -> 14700 | J25: =80*$C$25*$B$25 -> 16800 | K25: =90*$C$25*$B$25 -> 18900 | L25: =110*$C$25*$B$25 -> 23100 | M25: =90*$C$25*$B$25 -> 18900 | N25: =70*$C$25*$B$25 -> 14700 | O25: =80*$C$25*$B$25 -> 16800 | P25: =SUM(D25:O25) -> 213150
A26: APAR. 50% (CONTADO) | B26: 1575 | C26: 1 | D26: =3*$C$26*$B$26 -> 4725 | E26: =5*$C$26*$B$26 -> 7875 | F26: =6*$C$26*$B$26 -> 9450 | G26: =8*$C$26*$B$26 -> 12600 | H26: =5*$C$26*$B$26 -> 7875 | I26: =3*$C$26*$B$26 -> 4725 | J26: =5*$C$26*$B$26 -> 7875 | K26: =4*$C$26*$B$26 -> 6300 | L26: =4*$C$26*$B$26 -> 6300 | M26: =5*$C$26*$B$26 -> 7875 | N26: =3*$C$26*$B$26 -> 4725 | O26: =4*$C$26*$B$26 -> 6300 | P26: =SUM(D26:O26) -> 86625
A27: APAR. 50% (15 DÍAS) | B27: 1575 | C27: 1 | D27: =O8 -> 6400 | E27: =D26 -> 4725 | F27: =E26 -> 7875 | G27: =F26 -> 9450 | H27: =G26 -> 12600 | I27: =H26 -> 7875 | J27: =I26 -> 4725 | K27: =J26 -> 7875 | L27: =K26 -> 6300 | ... O27: =N26 -> 4725 | P27: =SUM(D27:O27) -> 86725
A28: SESIONES APARTO. | B28: 367.5 | C28: 1 | D28: =13*$C$28*$B$28 -> 4777.5 | E28: =20*$C$28*$B$28 -> 7350 | F28: =8*$C$28*$B$28 -> 2940 | G28: =0*$C$28*$B$28 -> 0 | H28: =18*$C$28*$B$28 -> 6615 | I28: =0*$C$28*$B$28 -> 0 | J28: =12*$C$28*$B$28 -> 4410 | K28: =0*$C$28*$B$28 -> 0 | L28: =2*$C$28*$B$28 -> 735 | M28: =30*$C$28*$B$28 -> 11025 | N28: =25*$C$28*$B$28 -> 9187.5 | O28: =20*$C$28*$B$28 -> 7350 | P28: =SUM(D28:O28) -> 54390
A29: RADIO FACIAL | B29: 262.5 | C29: 1 | D29: =30*$C$29*$B$29 -> 7875 | E29: =30*$C$29*$B$29 -> 7875 | F29: =30*$C$29*$B$29 -> 7875 | G29: =30*$C$29*$B$29 -> 7875 | H29: =30*$C$29*$B$29 -> 7875 | I29: =10*$C$29*$B$29 -> 2625 | J29: =19*$C$29*$B$29 -> 4987.5 | K29: =25*$C$29*$B$29 -> 6562.5 | L29: =30*$C$29*$B$29 -> 7875 | M29: =17*$C$29*$B$29 -> 4462.5 | N29: =35*$C$29*$B$29 -> 9187.5 | O29: =30*$C$29*$B$29 -> 7875 | P29: =SUM(D29:O29) -> 82950
A30: MASAJES | B30: 525 | C30: 1 | D30: =18*$C$30*$B$30 -> 9450 | E30: =39*$C$30*$B$30 -> 20475 | F30: =40*$C$30*$B$30 -> 21000 | G30: =25*$C$30*$B$30 -> 13125 | H30: =35*$C$30*$B$30 -> 18375 | I30: =30*$C$30*$B$30 -> 15750 | J30: =35*$C$30*$B$30 -> 18375 | K30: =35*$C$30*$B$30 -> 18375 | L30: =50*$C$30*$B$30 -> 26250 | M30: =30*$C$30*$B$30 -> 15750 | N30: =16*$C$30*$B$30 -> 8400 | O30: =14*$C$30*$B$30 -> 7350 | P30: =SUM(D30:O30) -> 192675
A31: PTO ENTRADAS | D31: =D22+D23+D24+D25+D26+D27+D28+D29+D30 -> 60317.5 | E31: =E22+E23+E24+E25+E26+E27+E28+E29+E30 -> 78855 | F31: =F22+F23+F24+F25+F26+F27+F28+F29+F30 -> 92190 | G31: =G22+G23+G24+G25+G26+G27+G28+G29+G30 -> 77490 | H31: =H22+H23+H24+H25+H26+H27+H28+H29+H30 -> 94710 | I31: =I22+I23+I24+I25+I26+I27+I28+I29+I30 -> 58065 | J31: =J22+J23+J24+J25+J26+J27+J28+J29+J30 -> 75022.5 | K31: =K22+K23+K24+K25+K26+K27+K28+K29+K30 -> 78750 | ... O31: =O22+O23+O24+O25+O26+O27+O28+O29+O30 -> 80325 | P31: =SUM(D31:O31) -> 949142.5
A32: VENTAS | D32: =D22+D23+D24+D25+D26+E27+D28+D29+D30 -> 58642.5 | E32: =E22+E23+E24+E25+E26+F27+E28+E29+E30 -> 82005 | F32: =F22+F23+F24+F25+F26+G27+F28+F29+F30 -> 93765 | G32: =G22+G23+G24+G25+G26+H27+G28+G29+G30 -> 80640 | H32: =H22+H23+H24+H25+H26+I27+H28+H29+H30 -> 89985 | I32: =I22+I23+I24+I25+I26+J27+I28+I29+I30 -> 54915 | J32: =J22+J23+J24+J25+J26+K27+J28+J29+J30 -> 78172.5 | K32: =K22+K23+K24+K25+K26+L27+K28+K29+K30 -> 77175 | ... N32: =N22+N23+N24+N25+N26+O27+N28+N29+N30 -> 78750 | O32: =O22+O23+O24+O25+O26+D45+O28+O29+O30 -> 81900 | P32: =SUM(D32:O32) -> 949042.5
A34: VENTAS INFLACIÓN | D34: =D32*1.05 -> 61574.625 | E34: =E32*1.05 -> 86105.25 | F34: =F32*1.05 -> 98453.25 | G34: =G32*1.05 -> 84672 | H34: =H32*1.05 -> 94484.25 | I34: =I32*1.05 -> 57660.75 | J34: =J32*1.05 -> 82081.125 | K34: =K32*1.05 -> 81033.75 | ... O34: =O32*1.05 -> 85995 | P34: =SUM(D34:O34) -> 996494.62
A35: AUMENTO 10% | D35: =D34*1.1 -> 67732.088 | E35: =E34*1.1 -> 94715.775 | F35: =F34*1.1 -> 108298.58 | G35: =G34*1.1 -> 93139.2 | H35: =H34*1.1 -> 103932.68 | I35: =I34*1.1 -> 63426.825 | J35: =J34*1.1 -> 90289.238 | K35: =K34*1.1 -> 89137.125 | ... O35: =O34*1.1 -> 94594.5 | P35: =SUM(D35:O35) -> 1096144.1
A38: 2022
A39: CONCEPTO | B39: COSTO | C39: PERSONAL REQUERIDO | D39: ENERO | E39: FEBRERO | F39: MARZO | G39: ABRIL | H39: MAYO | I39: JUNIO | J39: JULIO | K39: AGOSTO | L39: SEPTIEMBRE | M39: OCTUBRE | N39: NOVIEMBRE | O39: DICIEMBRE | P39: TOTAL | S39: ENERO | T39: FEBRERO | U39: MARZO | V39: ABRIL | W39: MAYO | X39: JUNIO | Y39: JULIO | Z39: AGOSTO | AA39: SEPTIEMBRE | AB39: OCTUBRE | AC39: NOVIEMBRE | AD39: DICIEMBRE
A40: MANICURE | B40: 165.38 | C40: 1 | D40: =S40*$C$40*$B$40 -> 4961.4 | E40: =T40*$C$40*$B$40 -> 4961.4 | F40: =U40*$C$40*$B$40 -> 9922.8 | G40: =V40*$C$40*$B$40 -> 8269 | H40: =W40*$C$40*$B$40 -> 9922.8 | I40: =X40*$C$40*$B$40 -> 5788.3 | J40: =Y40*$C$40*$B$40 -> 8269 | K40: =Z40*$C$40*$B$40 -> 6615.2 | ... O40: =AD40*$C$40*$B$40 -> 11576.6 | P40: =SUM(D40:O40) -> 92612.8 | S40: 30 | T40: 30 | U40: 60 | V40: 50 | W40: 60 | X40: 35 | Y40: 50 | Z40: 40 | AA40: 40 | AB40: 45 | AC40: 50 | AD40: 70
A41: PEDICURE | B41: 220.5 | C41: 1 | D41: =S41*$C$41*$B$41 -> 4410 | E41: =T41*$C$41*$B$41 -> 4410 | F41: =U41*$C$41*$B$41 -> 9922.5 | G41: =V41*$C$41*$B$41 -> 6615 | H41: =W41*$C$41*$B$41 -> 8820 | I41: =X41*$C$41*$B$41 -> 6615 | J41: =Y41*$C$41*$B$41 -> 0 | K41: =Z41*$C$41*$B$41 -> 4410 | ... O41: =AD41*$C$41*$B$41 -> 9922.5 | P41: =SUM(D41:O41) -> 77395.5 | S41: 20 | T41: 20 | U41: 45 | V41: 30 | W41: 40 | X41: 30 | Y41: 0 | Z41: 20 | AA41: 28 | AB41: 28 | AC41: 45 | AD41: 45
A42: FACIALES | B42: 330.75 | C42: 1 | D42: =S42*$C$42*$B$42 -> 8268.75 | E42: =T42*$C$42*$B$42 -> 6615 | F42: =U42*$C$42*$B$42 -> 11576.25 | G42: =V42*$C$42*$B$42 -> 8268.75 | H42: =W42*$C$42*$B$42 -> 6615 | I42: =X42*$C$42*$B$42 -> 4961.25 | J42: =Y42*$C$42*$B$42 -> 9922.5 | K42: =Z42*$C$42*$B$42 -> 8268.75 | ... O42: =AD42*$C$42*$B$42 -> 6615 | P42: =SUM(D42:O42) -> 95256 | S42: 25 | T42: 20 | U42: 35 | V42: 25 | W42: 20 | X42: 15 | Y42: 30 | Z42: 25 | AA42: 23 | AB42: 25 | AC42: 25 | AD42: 20
A43: DEPILACIONES | B43: 220.5 | C43: 1 | D43: =S43*$C$43*$B$43 -> 13230 | E43: =T43*$C$43*$B$43 -> 16978.5 | F43: =U43*$C$43*$B$43 -> 22050 | G43: =V43*$C$43*$B$43 -> 19845 | H43: =W43*$C$43*$B$43 -> 17640 | I43: =X43*$C$43*$B$43 -> 13230 | J43: =Y43*$C$43*$B$43 -> 17640 | K43: =Z43*$C$43*$B$43 -> 14332.5 | ... O43: =AD43*$C$43*$B$43 -> 8820 | P43: =SUM(D43:O43) -> 187866 | S43: 60 | T43: 77 | U43: 100 | V43: 90 | W43: 80 | X43: 60 | Y43: 80 | Z43: 65 | AA43: 75 | AB43: 75 | AC43: 50 | AD43: 40
A44: APAR. 50% (CONTADO) | B44: =3307.5/2 -> 1653.75 | C44: 1 | D44: =S44*$C$44*$B$44 -> 8268.75 | E44: =T44*$C$44*$B$44 -> 6615 | F44: =U44*$C$44*$B$44 -> 4961.25 | G44: =V44*$C$44*$B$44 -> 6615 | H44: =W44*$C$44*$B$44 -> 4961.25 | I44: =X44*$C$44*$B$44 -> 3307.5 | J44: =Y44*$C$44*$B$44 -> 3307.5 | K44: =Z44*$C$44*$B$44 -> 4961.25 | ... O44: =AD44*$C$44*$B$44 -> 3307.5 | P44: =SUM(D44:O44) -> 66150 | S44: 5 | T44: 4 | U44: 3 | V44: 4 | W44: 3 | X44: 2 | Y44: 2 | Z44: 3 | AA44: 4 | AB44: 5 | AC44: 3 | AD44: 2
A45: APAR. 50% (15 DÍAS) | B45: =B44 -> 1653.75 | C45: 1 | D45: =O26 -> 6300 | E45: =D44 -> 8268.75 | F45: =E44 -> 6615 | G45: =F44 -> 4961.25 | H45: =G44 -> 6615 | I45: =H44 -> 4961.25 | J45: =I44 -> 3307.5 | K45: =J44 -> 3307.5 | L45: =K44 -> 4961.25 | ... O45: =N44 -> 4961.25 | P45: =SUM(D45:O45) -> 69142.5
A46: SESIONES APARTO. | B46: 385.88 | C46: 1 | D46: =S46*$C$46*$B$46 -> 9647 | E46: =T46*$C$46*$B$46 -> 8489.36 | F46: =U46*$C$46*$B$46 -> 11576.4 | G46: =V46*$C$46*$B$46 -> 7717.6 | H46: =W46*$C$46*$B$46 -> 11576.4 | I46: =X46*$C$46*$B$46 -> 6945.84 | J46: =Y46*$C$46*$B$46 -> 7717.6 | K46: =Z46*$C$46*$B$46 -> 9647 | ... O46: =AD46*$C$46*$B$46 -> 11576.4 | P46: =SUM(D46:O46) -> 84893.6 | S46: 25 | T46: 22 | U46: 30 | V46: 20 | W46: 30 | X46: 18 | Y46: 20 | Z46: 25 | AA46: 0 | AB46: 0 | AC46: 0 | AD46: 30
A47: RADIO FACIAL | B47: 275.63 | C47: 1 | D47: =S47*$C$47*$B$47 -> 6890.75 | E47: =T47*$C$47*$B$47 -> 8268.9 | F47: =U47*$C$47*$B$47 -> 6615.12 | G47: =V47*$C$47*$B$47 -> 8268.9 | H47: =W47*$C$47*$B$47 -> 11025.2 | I47: =X47*$C$47*$B$47 -> 6890.75 | J47: =Y47*$C$47*$B$47 -> 11025.2 | K47: =Z47*$C$47*$B$47 -> 8268.9 | ... O47: =AD47*$C$47*$B$47 -> 12403.35 | P47: =SUM(D47:O47) -> 115488.97 | S47: 25 | T47: 30 | U47: 24 | V47: 30 | W47: 40 | X47: 25 | Y47: 40 | Z47: 30 | AA47: 60 | AB47: 35 | AC47: 35 | AD47: 45
A48: MASAJES | B48: 551.25 | C48: 1 | D48: =S48*$C$48*$B$48 -> 13781.25 | E48: =T48*$C$48*$B$48 -> 22050 | F48: =U48*$C$48*$B$48 -> 16537.5 | G48: =V48*$C$48*$B$48 -> 16537.5 | H48: =W48*$C$48*$B$48 -> 16537.5 | I48: =X48*$C$48*$B$48 -> 16537.5 | J48: =Y48*$C$48*$B$48 -> 16537.5 | K48: =Z48*$C$48*$B$48 -> 16537.5 | ... O48: =AD48*$C$48*$B$48 -> 16537.5 | P48: =SUM(D48:O48) -> 222153.75 | S48: 25 | T48: 40 | U48: 30 | V48: 30 | W48: 30 | X48: 30 | Y48: 30 | Z48: 30 | AA48: 48 | AB48: 40 | AC48: 40 | AD48: 30
A49: YOGA | B49: 610 | C49: 1 | D49: =S49*$C$49*$B$49 -> 4270 | E49: =T49*$C$49*$B$49 -> 9760 | F49: =U49*$C$49*$B$49 -> 10370 | G49: =V49*$C$49*$B$49 -> 10370 | H49: =W49*$C$49*$B$49 -> 12200 | I49: =X49*$C$49*$B$49 -> 10980 | J49: =Y49*$C$49*$B$49 -> 12200 | K49: =Z49*$C$49*$B$49 -> 12810 | ... O49: =AD49*$C$49*$B$49 -> 10370 | P49: =SUM(D49:O49) -> 134810 | S49: 7 | T49: 16 | U49: 17 | V49: 17 | W49: 20 | X49: 18 | Y49: 20 | Z49: 21 | AA49: 21 | AB49: 23 | AC49: 24 | AD49: 17
A50: PTO ENTRADAS | D50: =D40+D41+D42+D43+D44+D46+D47+D48+D45+D49 -> 80027.9 | E50: =E40+E41+E42+E43+E44+E46+E47+E48+E45+E49 -> 96416.91 | F50: =F40+F41+F42+F43+F44+F46+F47+F48+F45+F49 -> 110146.82 | G50: =G40+G41+G42+G43+G44+G46+G47+G48+G45+G49 -> 97468 | H50: =H40+H41+H42+H43+H44+H46+H47+H48+H45+H49 -> 105913.15 | I50: =I40+I41+I42+I43+I44+I46+I47+I48+I45+I49 -> 80217.39 | J50: =J40+J41+J42+J43+J44+J46+J47+J48+J45+J49 -> 89926.8 | K50: =K40+K41+K42+K43+K44+K46+K47+K48+K45+K49 -> 89158.6 | ... O50: =O40+O41+O42+O43+O44+O46+O47+O48+O45+O49 -> 96090.1 | P50: =SUM(D50:O50) -> 1145769.1
A51: VENTAS | D51: =D40+D41+D42+D43+D44+E45+D46+D47+D48+D49 -> 81996.65 | E51: =E40+E41+E42+E43+E44+F45+E46+E47+E48+E49 -> 94763.16 | F51: =F40+F41+F42+F43+F44+G45+F46+F47+F48+F49 -> 108493.07 | G51: =G40+G41+G42+G43+G44+H45+G46+G47+G48+G49 -> 99121.75 | H51: =H40+H41+H42+H43+H44+I45+H46+H47+H48+H49 -> 104259.4 | I51: =I40+I41+I42+I43+I44+J45+I46+I47+I48+I49 -> 78563.64 | J51: =J40+J41+J42+J43+J44+K45+J46+J47+J48+J49 -> 89926.8 | K51: =K40+K41+K42+K43+K44+L45+K46+K47+K48+K49 -> 90812.35 | ... N51: =N40+N41+N42+N43+N44+O45+N46+N47+N48+N49 -> 93744.8 | O51: =O40+O41+O42+O43+O44+O46+O47+O48+O49+D64 -> 94436.35 | P51: =SUM(D51:O51) -> 1142776.6
A53: VENTAS INFLACIÓN | D53: =D51*1.05 -> 86096.482 | E53: =E51*1.05 -> 99501.318 | F53: =F51*1.05 -> 113917.72 | G53: =G51*1.05 -> 104077.84 | H53: =H51*1.05 -> 109472.37 | I53: =I51*1.05 -> 82491.822 | J53: =J51*1.05 -> 94423.14 | K53: =K51*1.05 -> 95352.968 | ... O53: =O51*1.05 -> 99158.168 | P53: =SUM(D53:O53) -> 1199915.5
A54: AUMENTO 10% | D54: =D53*1.1 -> 94706.131 | E54: =E53*1.1 -> 109451.45 | F54: =F53*1.1 -> 125309.5 | G54: =G53*1.1 -> 114485.62 | H54: =H53*1.1 -> 120419.61 | I54: =I53*1.1 -> 90741.004 | J54: =J53*1.1 -> 103865.45 | K54: =K53*1.1 -> 104888.26 | ... O54: =O53*1.1 -> 109073.98 | P54: =SUM(D54:O54) -> 1319907
A57: 2023
A58: CONCEPTO | B58: COSTO | C58: PERSONAL REQUERIDO | D58: ENERO | E58: FEBRERO | F58: MARZO | G58: ABRIL | H58: MAYO | I58: JUNIO | J58: JULIO | K58: AGOSTO | L58: SEPTIEMBRE | M58: OCTUBRE | N58: NOVIEMBRE | O58: DICIEMBRE | P58: TOTAL | S58: ENERO | T58: FEBRERO | U58: MARZO | V58: ABRIL | W58: MAYO | X58: JUNIO | Y58: JULIO | Z58: AGOSTO | AA58: SEPTIEMBRE | AB58: OCTUBRE | AC58: NOVIEMBRE | AD58: DICIEMBRE
A59: MANICURE | B59: 173.64 | C59: 1 | D59: =S59*$C$59*$B$59 -> 7813.8 | E59: =T59*$C$59*$B$59 -> 7813.8 | F59: =U59*$C$59*$B$59 -> 7813.8 | G59: =V59*$C$59*$B$59 -> 8682 | H59: =W59*$C$59*$B$59 -> 9029.28 | I59: =X59*$C$59*$B$59 -> 6077.4 | J59: =Y59*$C$59*$B$59 -> 6945.6 | K59: =Z59*$C$59*$B$59 -> 7813.8 | ... O59: =AD59*$C$59*$B$59 -> 6945.6 | P59: =SUM(D59:O59) -> 93244.68 | S59: 45 | T59: 45 | U59: 45 | V59: 50 | W59: 52 | X59: 35 | Y59: 40 | Z59: 45 | AA59: 50 | AB59: 55 | AC59: 35 | AD59: 40
A60: PEDICURE | B60: 231.53 | C60: 1 | D60: =S60*$C$60*$B$60 -> 7408.96 | E60: =T60*$C$60*$B$60 -> 8103.55 | F60: =U60*$C$60*$B$60 -> 9261.2 | G60: =V60*$C$60*$B$60 -> 9261.2 | H60: =W60*$C$60*$B$60 -> 10418.85 | I60: =X60*$C$60*$B$60 -> 8103.55 | J60: =Y60*$C$60*$B$60 -> 9261.2 | K60: =Z60*$C$60*$B$60 -> 10418.85 | ... O60: =AD60*$C$60*$B$60 -> 11576.5 | P60: =SUM(D60:O60) -> 106966.86 | S60: 32 | T60: 35 | U60: 40 | V60: 40 | W60: 45 | X60: 35 | Y60: 40 | Z60: 45 | AA60: 35 | AB60: 35 | AC60: 30 | AD60: 50
A61: FACIALES | B61: 347.29 | C61: 1 | D61: =S61*$C$61*$B$61 -> 6945.8 | E61: =T61*$C$61*$B$61 -> 12155.15 | F61: =U61*$C$61*$B$61 -> 10418.7 | G61: =V61*$C$61*$B$61 -> 8682.25 | H61: =W61*$C$61*$B$61 -> 10418.7 | I61: =X61*$C$61*$B$61 -> 10418.7 | J61: =Y61*$C$61*$B$61 -> 6945.8 | K61: =Z61*$C$61*$B$61 -> 5209.35 | ... O61: =AD61*$C$61*$B$61 -> 5209.35 | P61: =SUM(D61:O61) -> 86822.5 | S61: 20 | T61: 35 | U61: 30 | V61: 25 | W61: 30 | X61: 30 | Y61: 20 | Z61: 15 | AA61: 20 | AB61: 0 | AC61: 10 | AD61: 15
A62: DEPILACIONES | B62: 231.53 | C62: 1 | D62: =S62*$C$62*$B$62 -> 17364.75 | E62: =T62*$C$62*$B$62 -> 13891.8 | F62: =U62*$C$62*$B$62 -> 25468.3 | G62: =V62*$C$62*$B$62 -> 16207.1 | H62: =W62*$C$62*$B$62 -> 16207.1 | I62: =X62*$C$62*$B$62 -> 16207.1 | J62: =Y62*$C$62*$B$62 -> 18522.4 | K62: =Z62*$C$62*$B$62 -> 23153 | ... O62: =AD62*$C$62*$B$62 -> 20837.7 | P62: =SUM(D62:O62) -> 241948.85 | S62: 75 | T62: 60 | U62: 110 | V62: 70 | W62: 70 | X62: 70 | Y62: 80 | Z62: 100 | AA62: 100 | AB62: 110 | AC62: 110 | AD62: 90
A63: APAR. 50% (CONTADO) | B63: =3472.88/2 -> 1736.44 | C63: 1 | D63: =S63*$C$63*$B$63 -> 6945.76 | E63: =T63*$C$63*$B$63 -> 5209.32 | F63: =U63*$C$63*$B$63 -> 10418.64 | G63: =V63*$C$63*$B$63 -> 6945.76 | H63: =W63*$C$63*$B$63 -> 3472.88 | I63: =X63*$C$63*$B$63 -> 5209.32 | J63: =Y63*$C$63*$B$63 -> 5209.32 | K63: =Z63*$C$63*$B$63 -> 5209.32 | ... O63: =AD63*$C$63*$B$63 -> 5209.32 | P63: =SUM(D63:O63) -> 71194.04 | S63: 4 | T63: 3 | U63: 6 | V63: 4 | W63: 2 | X63: 3 | Y63: 3 | Z63: 3 | AA63: 3 | AB63: 4 | AC63: 3 | AD63: 3
A64: APAR. 50% (15 DÍAS) | B64: =B63 -> 1736.44 | C64: 1 | D64: =O44 -> 3307.5 | E64: =D63 -> 6945.76 | F64: =E63 -> 5209.32 | G64: =F63 -> 10418.64 | H64: =G63 -> 6945.76 | I64: =H63 -> 3472.88 | J64: =I63 -> 5209.32 | K64: =J63 -> 5209.32 | L64: =K63 -> 5209.32 | ... O64: =N63 -> 5209.32 | P64: =SUM(D64:O64) -> 69292.22
A65: SESIONES APARTO. | B65: 405.17 | C65: 1 | D65: =S65*$C$65*$B$65 -> 0 | E65: =T65*$C$65*$B$65 -> 10129.25 | F65: =U65*$C$65*$B$65 -> 8103.4 | G65: =V65*$C$65*$B$65 -> 0 | H65: =W65*$C$65*$B$65 -> 8103.4 | I65: =X65*$C$65*$B$65 -> 6077.55 | J65: =Y65*$C$65*$B$65 -> 12155.1 | K65: =Z65*$C$65*$B$65 -> 0 | ... O65: =AD65*$C$65*$B$65 -> 12155.1 | P65: =SUM(D65:O65) -> 85085.7 | S65: 0 | T65: 25 | U65: 20 | V65: 0 | W65: 20 | X65: 15 | Y65: 30 | Z65: 0 | AA65: 30 | AB65: 25 | AC65: 15 | AD65: 30
A66: RADIO FACIAL | B66: 289.41 | C66: 1 | D66: =S66*$C$66*$B$66 -> 8682.3 | E66: =T66*$C$66*$B$66 -> 7235.25 | F66: =U66*$C$66*$B$66 -> 7235.25 | G66: =V66*$C$66*$B$66 -> 11576.4 | H66: =W66*$C$66*$B$66 -> 14470.5 | I66: =X66*$C$66*$B$66 -> 7235.25 | J66: =Y66*$C$66*$B$66 -> 8682.3 | K66: =Z66*$C$66*$B$66 -> 12155.22 | ... O66: =AD66*$C$66*$B$66 -> 8682.3 | P66: =SUM(D66:O66) -> 118368.69 | S66: 30 | T66: 25 | U66: 25 | V66: 40 | W66: 50 | X66: 25 | Y66: 30 | Z66: 42 | AA66: 40 | AB66: 30 | AC66: 42 | AD66: 30
A67: MASAJES | B67: 578.81 | C67: 1 | D67: =S67*$C$67*$B$67 -> 17364.3 | E67: =T67*$C$67*$B$67 -> 24310.02 | F67: =U67*$C$67*$B$67 -> 23152.4 | G67: =V67*$C$67*$B$67 -> 28940.5 | H67: =W67*$C$67*$B$67 -> 27782.88 | I67: =X67*$C$67*$B$67 -> 11576.2 | J67: =Y67*$C$67*$B$67 -> 19100.73 | K67: =Z67*$C$67*$B$67 -> 23152.4 | ... O67: =AD67*$C$67*$B$67 -> 20258.35 | P67: =SUM(D67:O67) -> 273777.13 | S67: 30 | T67: 42 | U67: 40 | V67: 50 | W67: 48 | X67: 20 | Y67: 33 | Z67: 40 | AA67: 50 | AB67: 45 | AC67: 40 | AD67: 35
A68: YOGA | B68: 640.5 | C68: 1 | D68: =S68*$C$68*$B$68 -> 15372 | E68: =T68*$C$68*$B$68 -> 16012.5 | F68: =U68*$C$68*$B$68 -> 16653 | G68: =V68*$C$68*$B$68 -> 17293.5 | H68: =W68*$C$68*$B$68 -> 17293.5 | I68: =X68*$C$68*$B$68 -> 16012.5 | J68: =Y68*$C$68*$B$68 -> 12810 | K68: =Z68*$C$68*$B$68 -> 12810 | ... O68: =AD68*$C$68*$B$68 -> 22417.5 | P68: =SUM(D68:O68) -> 192790.5 | S68: 24 | T68: 25 | U68: 26 | V68: 27 | W68: 27 | X68: 25 | Y68: 20 | Z68: 20 | AA68: 22 | AB68: 25 | AC68: 25 | AD68: 35
A69: PTO ENTRADAS | D69: =D59+D60+D61+D62+D63+D65+D66+D67+D64+D68 -> 91205.17 | E69: =E59+E60+E61+E62+E63+E65+E66+E67+E64+E68 -> 111806.4 | F69: =F59+F60+F61+F62+F63+F65+F66+F67+F64+F68 -> 123734.01 | G69: =G59+G60+G61+G62+G63+G65+G66+G67+G64+G68 -> 118007.35 | H69: =H59+H60+H61+H62+H63+H65+H66+H67+H64+H68 -> 124142.85 | I69: =I59+I60+I61+I62+I63+I65+I66+I67+I64+I68 -> 90390.45 | J69: =J59+J60+J61+J62+J63+J65+J66+J67+J64+J68 -> 104841.77 | K69: =K59+K60+K61+K62+K63+K65+K66+K67+K64+K68 -> 105131.26 | ... O69: =O59+O60+O61+O62+O63+O65+O66+O67+O64+O68 -> 118501.04 | P69: =SUM(D69:O69) -> 1339491.2
A70: VENTAS | D70: =D59+D60+D61+D62+D63+E64+D65+D66+D67+D68 -> 94843.43 | E70: =E59+E60+E61+E62+E63+F64+E65+E66+E67+E68 -> 110069.96 | F70: =F59+F60+F61+F62+F63+G64+F65+F66+F67+F68 -> 128943.33 | G70: =G59+G60+G61+G62+G63+H64+G65+G66+G67+G68 -> 114534.47 | H70: =H59+H60+H61+H62+H63+I64+H65+H66+H67+H68 -> 120669.97 | I70: =I59+I60+I61+I62+I63+J64+I65+I66+I67+I68 -> 92126.89 | J70: =J59+J60+J61+J62+J63+K64+J65+J66+J67+J68 -> 104841.77 | K70: =K59+K60+K61+K62+K63+L64+K65+K66+K67+K68 -> 105131.26 | ... N70: =N59+N60+N61+N62+N63+O64+N65+N66+N67+N68 -> 109780.81 | O70: =O59+O60+O61+O62+O63+O65+O66+O67+O68+O64 -> 118501.04 | P70: =SUM(D70:O70) -> 1341393
A72: VENTAS INFLACIÓN | D72: =D70*1.05 -> 99585.602 | E72: =E70*1.05 -> 115573.46 | F72: =F70*1.05 -> 135390.5 | G72: =G70*1.05 -> 120261.19 | H72: =H70*1.05 -> 126703.47 | I72: =I70*1.05 -> 96733.235 | J72: =J70*1.05 -> 110083.86 | K72: =K70*1.05 -> 110387.82 | ... O72: =O70*1.05 -> 124426.09 | P72: =SUM(D72:O72) -> 1408462.6
A73: AUMENTO 10% | D73: =D72*1.1 -> 109544.16 | E73: =E72*1.1 -> 127130.8 | F73: =F72*1.1 -> 148929.55 | G73: =G72*1.1 -> 132287.31 | H73: =H72*1.1 -> 139373.82 | I73: =I72*1.1 -> 106406.56 | J73: =J72*1.1 -> 121092.24 | K73: =K72*1.1 -> 121426.61 | ... O73: =O72*1.1 -> 136868.7 | P73: =SUM(D73:O73) -> 1549308.9
A76: 2024
A77: CONCEPTO | B77: COSTO | C77: PERSONAL REQUERIDO | D77: ENERO | E77: FEBRERO | F77: MARZO | G77: ABRIL | H77: MAYO | I77: JUNIO | J77: JULIO | K77: AGOSTO | L77: SEPTIEMBRE | M77: OCTUBRE | N77: NOVIEMBRE | O77: DICIEMBRE | P77: TOTAL | S77: ENERO | T77: FEBRERO | U77: MARZO | V77: ABRIL | W77: MAYO | X77: JUNIO | Y77: JULIO | Z77: AGOSTO | AA77: SEPTIEMBRE | AB77: OCTUBRE | AC77: NOVIEMBRE | AD77: DICIEMBRE
A78: MANICURE | B78: 182.33 | C78: 1 | D78: =S78*$B$78*$C$78 -> 6928.54 | E78: =T78*$B$78*$C$78 -> 9116.5 | F78: =U78*$B$78*$C$78 -> 9116.5 | G78: =V78*$B$78*$C$78 -> 7293.2 | H78: =W78*$B$78*$C$78 -> 10028.15 | I78: =X78*$B$78*$C$78 -> 4558.25 | J78: =Y78*$B$78*$C$78 -> 4558.25 | K78: =Z78*$B$78*$C$78 -> 5469.9 | ... O78: =AD78*$B$78*$C$78 -> 9116.5 | P78: =SUM(D78:O78) -> 91165 | S78: 38 | T78: 50 | U78: 50 | V78: 40 | W78: 55 | X78: 25 | Y78: 25 | Z78: 30 | AA78: 50 | AB78: 45 | AC78: 42 | AD78: 50
A79: PEDICURE | B79: 243.1 | C79: 1 | D79: =S79*$B$79*$C$79 -> 9724 | E79: =T79*$B$79*$C$79 -> 9724 | F79: =U79*$B$79*$C$79 -> 12155 | G79: =V79*$B$79*$C$79 -> 9724 | H79: =W79*$B$79*$C$79 -> 9724 | I79: =X79*$B$79*$C$79 -> 4862 | J79: =Y79*$B$79*$C$79 -> 7293 | K79: =Z79*$B$79*$C$79 -> 6077.5 | ... O79: =AD79*$B$79*$C$79 -> 12155 | P79: =SUM(D79:O79) -> 110610.5 | S79: 40 | T79: 40 | U79: 50 | V79: 40 | W79: 40 | X79: 20 | Y79: 30 | Z79: 25 | AA79: 50 | AB79: 40 | AC79: 30 | AD79: 50
A80: FACIALES | B80: 364.65 | C80: 1 | D80: =S80*$B$80*$C$80 -> 2187.9 | E80: =T80*$B$80*$C$80 -> 10939.5 | F80: =U80*$B$80*$C$80 -> 9116.25 | G80: =V80*$B$80*$C$80 -> 7293 | H80: =W80*$B$80*$C$80 -> 12762.75 | I80: =X80*$B$80*$C$80 -> 2917.2 | J80: =Y80*$B$80*$C$80 -> 7293 | K80: =Z80*$B$80*$C$80 -> 7293 | ... O80: =AD80*$B$80*$C$80 -> 5469.75 | P80: =SUM(D80:O80) -> 86422.05 | S80: 6 | T80: 30 | U80: 25 | V80: 20 | W80: 35 | X80: 8 | Y80: 20 | Z80: 20 | AA80: 20 | AB80: 20 | AC80: 18 | AD80: 15
A81: DEPILACIONES | B81: 243.1 | C81: 1 | D81: =S81*$B$81*$C$81 -> 24310 | E81: =T81*$B$81*$C$81 -> 14586 | F81: =U81*$B$81*$C$81 -> 29172 | G81: =V81*$B$81*$C$81 -> 24310 | H81: =W81*$B$81*$C$81 -> 21879 | I81: =X81*$B$81*$C$81 -> 18232.5 | J81: =Y81*$B$81*$C$81 -> 24310 | K81: =Z81*$B$81*$C$81 -> 26741 | ... O81: =AD81*$B$81*$C$81 -> 26741 | P81: =SUM(D81:O81) -> 290261.4 | S81: 100 | T81: 60 | U81: 120 | V81: 100 | W81: 90 | X81: 75 | Y81: 100 | Z81: 110 | AA81: 120 | AB81: 87 | AC81: 122 | AD81: 110
A82: APAR. 50% (CONTADO) | B82: =3646.52/2 -> 1823.26 | C82: 1 | D82: =S82*$B$82*$C$82 -> 9116.3 | E82: =T82*$B$82*$C$82 -> 7293.04 | F82: =U82*$B$82*$C$82 -> 5469.78 | G82: =V82*$B$82*$C$82 -> 7293.04 | H82: =W82*$B$82*$C$82 -> 7293.04 | I82: =X82*$B$82*$C$82 -> 10939.56 | J82: =Y82*$B$82*$C$82 -> 9116.3 | K82: =Z82*$B$82*$C$82 -> 7293.04 | ... O82: =AD82*$B$82*$C$82 -> 7293.04 | P82: =SUM(D82:O82) -> 94809.52 | S82: 5 | T82: 4 | U82: 3 | V82: 4 | W82: 4 | X82: 6 | Y82: 5 | Z82: 4 | AA82: 4 | AB82: 5 | AC82: 4 | AD82: 4
A83: APAR. 50% (15 DÍAS) | B83: =B82 -> 1823.26 | C83: 1 | D83: =O64 -> 5209.32 | E83: =D82 -> 9116.3 | F83: =E82 -> 7293.04 | G83: =F82 -> 5469.78 | H83: =G82 -> 7293.04 | I83: =H82 -> 7293.04 | J83: =I82 -> 10939.56 | K83: =J82 -> 9116.3 | L83: =K82 -> 7293.04 | ... O83: =N82 -> 7293.04 | P83: =SUM(D83:O83) -> 92725.8
A84: SESIONES APARTO. | B84: 425.43 | C84: 1 | D84: =S84*$B$84*$C$84 -> 0 | E84: =T84*$B$84*$C$84 -> 14039.19 | F84: =U84*$B$84*$C$84 -> 12762.9 | G84: =V84*$B$84*$C$84 -> 12762.9 | H84: =W84*$B$84*$C$84 -> 12762.9 | I84: =X84*$B$84*$C$84 -> 3403.44 | J84: =Y84*$B$84*$C$84 -> 8508.6 | K84: =Z84*$B$84*$C$84 -> 8508.6 | ... O84: =AD84*$B$84*$C$84 -> 12762.9 | P84: =SUM(D84:O84) -> 113164.38 | S84: 0 | T84: 33 | U84: 30 | V84: 30 | W84: 30 | X84: 8 | Y84: 20 | Z84: 20 | AA84: 20 | AB84: 30 | AC84: 15 | AD84: 30
A85: RADIO FACIAL | B85: 303.88 | C85: 1 | D85: =S85*$B$85*$C$85 -> 12155.2 | E85: =T85*$B$85*$C$85 -> 9116.4 | F85: =U85*$B$85*$C$85 -> 15194 | G85: =V85*$B$85*$C$85 -> 10028.04 | H85: =W85*$B$85*$C$85 -> 9116.4 | I85: =X85*$B$85*$C$85 -> 6077.6 | J85: =Y85*$B$85*$C$85 -> 9116.4 | K85: =Z85*$B$85*$C$85 -> 9116.4 | ... O85: =AD85*$B$85*$C$85 -> 9116.4 | P85: =SUM(D85:O85) -> 116386.04 | S85: 40 | T85: 30 | U85: 50 | V85: 33 | W85: 30 | X85: 20 | Y85: 30 | Z85: 30 | AA85: 40 | AB85: 30 | AC85: 20 | AD85: 30
A86: MASAJES | B86: 607.75 | C86: 1 | D86: =S86*$B$86*$C$86 -> 18232.5 | E86: =T86*$B$86*$C$86 -> 27348.75 | F86: =U86*$B$86*$C$86 -> 27348.75 | G86: =V86*$B$86*$C$86 -> 27348.75 | H86: =W86*$B$86*$C$86 -> 24310 | I86: =X86*$B$86*$C$86 -> 18232.5 | J86: =Y86*$B$86*$C$86 -> 21271.25 | K86: =Z86*$B$86*$C$86 -> 24310 | ... O86: =AD86*$B$86*$C$86 -> 18232.5 | P86: =SUM(D86:O86) -> 291720 | S86: 30 | T86: 45 | U86: 45 | V86: 45 | W86: 40 | X86: 30 | Y86: 35 | Z86: 40 | AA86: 45 | AB86: 50 | AC86: 45 | AD86: 30
A87: YOGA | B87: 672.53 | C87: 1 | D87: =S87*$B$87*$C$87 -> 26901.2 | E87: =T87*$B$87*$C$87 -> 26901.2 | F87: =U87*$B$87*$C$87 -> 26901.2 | G87: =V87*$B$87*$C$87 -> 26901.2 | H87: =W87*$B$87*$C$87 -> 28918.79 | I87: =X87*$B$87*$C$87 -> 28246.26 | J87: =Y87*$B$87*$C$87 -> 28246.26 | K87: =Z87*$B$87*$C$87 -> 26901.2 | ... O87: =AD87*$B$87*$C$87 -> 29591.32 | P87: =SUM(D87:O87) -> 340972.71 | S87: 40 | T87: 40 | U87: 40 | V87: 40 | W87: 43 | X87: 42 | Y87: 42 | Z87: 40 | AA87: 45 | AB87: 45 | AC87: 46 | AD87: 44
A88: PTO ENTRADAS | D88: =D78+D79+D80+D81+D82+D84+D85+D86+D83+D87 -> 114764.96 | E88: =E78+E79+E80+E81+E82+E84+E85+E86+E83+E87 -> 138180.88 | F88: =F78+F79+F80+F81+F82+F84+F85+F86+F83+F87 -> 154529.42 | G88: =G78+G79+G80+G81+G82+G84+G85+G86+G83+G87 -> 138423.91 | H88: =H78+H79+H80+H81+H82+H84+H85+H86+H83+H87 -> 144088.07 | I88: =I78+I79+I80+I81+I82+I84+I85+I86+I83+I87 -> 104762.35 | J88: =J78+J79+J80+J81+J82+J84+J85+J86+J83+J87 -> 130652.62 | K88: =K78+K79+K80+K81+K82+K84+K85+K86+K83+K87 -> 130826.94 | ... O88: =O78+O79+O80+O81+O82+O84+O85+O86+O83+O87 -> 137771.45 | P88: =SUM(D88:O88) -> 1628237.4
A89: VENTAS | D89: =D78+D79+D80+D81+D82+E83+D84+D85+D86+D87 -> 118671.94 | E89: =E78+E79+E80+E81+E82+F83+E84+E85+E86+E87 -> 136357.62 | F89: =F78+F79+F80+F81+F82+G83+F84+F85+F86+F87 -> 152706.16 | G89: =G78+G79+G80+G81+G82+H83+G84+G85+G86+G87 -> 140247.17 | H89: =H78+H79+H80+H81+H82+I83+H84+H85+H86+H87 -> 144088.07 | I89: =I78+I79+I80+I81+I82+J83+I84+I85+I86+I87 -> 108408.87 | J89: =J78+J79+J80+J81+J82+K83+J84+J85+J86+J87 -> 128829.36 | K89: =K78+K79+K80+K81+K82+L83+K84+K85+K86+K87 -> 129003.68 | ... N89: =N78+N79+N80+N81+N82+O83+N84+N85+N86+N87 -> 136503.02 | O89: =O78+O79+O80+O81+O82+O84+O85+O86+O87+O83 -> 137771.45 | P89: =SUM(D89:O89) -> 1630321.1
A91: VENTAS INFLACIÓN | D91: =D89*1.05 -> 124605.54 | E91: =E89*1.05 -> 143175.5 | F91: =F89*1.05 -> 160341.47 | G91: =G89*1.05 -> 147259.53 | H91: =H89*1.05 -> 151292.47 | I91: =I89*1.05 -> 113829.31 | J91: =J89*1.05 -> 135270.83 | K91: =K89*1.05 -> 135453.86 | ... O91: =O89*1.05 -> 144660.02 | P91: =SUM(D91:O91) -> 1711837.2
A92: AUMENTO 10% | D92: =D91*1.1 -> 137066.09 | E92: =E91*1.1 -> 157493.05 | F92: =F91*1.1 -> 176375.61 | G92: =G91*1.1 -> 161985.48 | H92: =H91*1.1 -> 166421.72 | I92: =I91*1.1 -> 125212.24 | J92: =J91*1.1 -> 148797.91 | K92: =K91*1.1 -> 148999.25 | ... O92: =O91*1.1 -> 159126.02 | P92: =SUM(D92:O92) -> 1883020.9

Sheet Flujos
A1: 2020
B2: ENE | C2: FEB | D2: MAR | E2: ABR | F2: MAY | G2: JUN | H2: JUL | I2: AGO | J2: SEP | K2: OCT | L2: NOV | M2: DIC | N2: TOTAL
A3: SALDO INICIAL | B3: 43154 | C3: =B18+B19 -> 34982.96 | D3: =C19+C18 -> 45640.76 | E3: =D18+D19 -> 67542.76 | F3: =E19+E18 -> 76182.3 | G3: =F18+F19 -> 82123.98 | H3: =G18+G19 -> 80096.58 | I3: =H18+H19 -> 77909.78 | J3: =I18+I19 -> 90093.58 | K3: =J18+J19 -> 109200.06 | L3: =K18+K19 -> 121938.46 | M3: =L18+L19 -> 129216.26 | N3: =SUM(B3:M3) -> 958081.48
A4: ENTRADAS DE EFECTIVO
A5: VENTA-SERVICIO | B5: =VENTAS!D13 -> 45200 | C5: =VENTAS!E13 -> 71050 | D5: =VENTAS!F13 -> 77800 | E5: =VENTAS!G13 -> 62400 | F5: =VENTAS!H13 -> 67900 | G5: =VENTAS!I13 -> 52300 | H5: =VENTAS!J13 -> 52050 | I5: =VENTAS!K13 -> 64200 | ... M5: =VENTAS!O13 -> 69700 | N5: =SUM(B5:M5) -> 778250
A6: TOTAL DE INGRESOS | B6: =B5+B3 -> 88354 | C6: =C5+C3 -> 106032.96 | D6: =D5+D3 -> 123440.76 | E6: =E5+E3 -> 129942.76 | F6: =F5+F3 -> 144082.3 | G6: =G5+G3 -> 134423.98 | H6: =H5+H3 -> 132146.58 | I6: =I5+I3 -> 142109.78 | ... M6: =M5+M3 -> 198916.26 | N6: =SUM(B6:M6) -> 1736331.5
A7: SALIDAS DE EFECTIVO
A8: LUZ(BIM) | B8: 0 | C8: 1800 | D8: 0 | E8: 1800 | F8: 0 | G8: 1800 | H8: 0 | I8: 1800 | J8: 0 | K8: 1800 | L8: 0 | M8: 1800 | N8: =SUM(B8:M8) -> 10800
A9: AGUA(BIM) | B9: 250 | C9: 320 | D9: 240 | E9: 250 | F9: 320 | G9: 250 | H9: 240 | I9: 250 | J9: 250 | K9: 320 | L9: 250 | M9: 350 | N9: =SUM(B9:M9) -> 3290
A10: TELEFONO E INTERNET | B10: 1000 | C10: 349 | D10: 349 | E10: 349 | F10: 349 | G10: 349 | H10: 349 | I10: 349 | J10: 349 | K10: 349 | L10: 349 | M10: 349 | N10: =SUM(B10:M10) -> 4839
A11: RENTA | B11: 18000 | C11: 9000 | D11: 9000 | E11: 9000 | F11: 9000 | G11: 9000 | H11: 9000 | I11: 9000 | J11: 9000 | K11: 9000 | L11: 9000 | M11: 9000 | N11: =SUM(B11:M11) -> 117000
A12: SEGURIDAD | B12: 0 | C12: 0 | D12: 0 | E12: 0 | F12: 0 | G12: 650 | H12: 0 | I12: 0 | J12: 0 | K12: 0 | L12: 0 | M12: 650 | N12: =SUM(B12:M12) -> 1300
A13: SUELDOS | B13: 19000 | C13: 19000 | D13: 19000 | E13: 19000 | F13: 19000 | G13: 19000 | H13: 19000 | I13: 19000 | J13: 19000 | K13: 19000 | L13: 19000 | M13: 19000 | N13: =SUM(B13:M13) -> 228000
A14: LAVANDERIA | B14: 544 | C14: 544 | D14: 544 | E14: 544 | F14: 544 | G14: 544 | H14: 544 | I14: 544 | J14: 544 | K14: 544 | L14: 544 | M14: 544 | N14: =SUM(B14:M14) -> 6528
A15: PAGO IMSS | B15: 0 | C15: 2800 | D15: 6000 | E15: 2800 | F15: 6000 | G15: 2800 | H15: 6000 | I15: 2800 | J15: 6000 | K15: 2800 | L15: 6000 | M15: 2800 | N15: =SUM(B15:M15) -> 46800
A16: INSUMOS | B16: 14577.04 | C16: 26579.2 | D16: 20765 | E16: 20017.46 | F16: 26745.32 | G16: 19934.4 | H16: 19103.8 | I16: 18273.2 | J16: 20100.52 | K16: 25748.6 | L16: 26579.2 | M16: 27409.8 | N16: =SUM(B16:M16) -> 265833.54
A17: SALDO ANTES DE MINIMO | B17: =B6-B8-B9-B10-B11-B12-B13-B14-B15-B16 -> 34982.96 | C17: =C6-C8-C9-C10-C11-C12-C13-C14-C15-C16 -> 45640.76 | D17: =D6-D8-D9-D10-D11-D12-D13-D14-D15-D16 -> 67542.76 | E17: =E6-E8-E9-E10-E11-E12-E13-E14-E15-E16 -> 76182.3 | F17: =F6-F8-F9-F10-F11-F12-F13-F14-F15-F16 -> 82123.98 | G17: =G6-G8-G9-G10-G11-G12-G13-G14-G15-G16 -> 80096.58 | H17: =H6-H8-H9-H10-H11-H12-H13-H14-H15-H16 -> 77909.78 | I17: =I6-I8-I9-I10-I11-I12-I13-I14-I15-I16 -> 90093.58 | ... M17: =M6-M8-M9-M10-M11-M12-M13-M14-M15-M16 -> 137013.46 | N17: =SUM(B17:M17) -> 1051940.9
A18: SALDO MINIMO DE OPERACIÓN | B18: 25000 | C18: 25000 | D18: 25000 | E18: 25000 | F18: 25000 | G18: 25000 | H18: 25000 | I18: 25000 | J18: 25000 | K18: 25000 | L18: 25000 | M18: 25000 | N18: =SUM(B18:M18) -> 300000
A19: EFECTIVO NUEVO DISPONIBLE | B19: =B17-B18 -> 9982.96 | C19: =C17-C18 -> 20640.76 | D19: =D17-D18 -> 42542.76 | E19: =E17-E18 -> 51182.3 | F19: =F17-F18 -> 57123.98 | G19: =G17-G18 -> 55096.58 | H19: =H17-H18 -> 52909.78 | I19: =I17-I18 -> 65093.58 | ... M19: =M17-M18 -> 112013.46 | N19: =N6-N8-N9-N10-N11-N12-N13-N14-N15-N16 -> 1051940.9
A21: 2021
B23: ENE | C23: FEB | D23: MAR | E23: ABR | F23: MAY | G23: JUN | H23: JUL | I23: AGO | J23: SEP | K23: OCT | L23: NOV | M23: DIC | N23: TOTAL
A24: SALDO INICIAL | B24: =M19+M18 -> 137013.46 | C24: =B41+B42 -> 130180.49 | D24: =C42+C41 -> 141635.91 | E24: =D41+D42 -> 160679.83 | F24: =E42+E41 -> 166396.04 | G24: =F41+F42 -> 186131.76 | H24: =G41+G42 -> 180374.26 | I24: =H41+H42 -> 186523.97 | J24: =I41+I42 -> 195767.64 | K24: =J41+J42 -> 212757.91 | L24: =K41+K42 -> 223066.16 | M24: =L41+L42 -> 232158.42 | N24: =SUM(B24:M24) -> 2152685.8
A25: ENTRADAS DE EFECTIVO
A26: VENTA-SERVICIO | B26: =VENTAS!D31 -> 60317.5 | C26: =VENTAS!E31 -> 78855 | D26: =VENTAS!F31 -> 92190 | E26: =VENTAS!G31 -> 77490 | F26: =VENTAS!H31 -> 94710 | G26: =VENTAS!I31 -> 58065 | H26: =VENTAS!J31 -> 75022.5 | I26: =VENTAS!K31 -> 78750 | ... M26: =VENTAS!O31 -> 80325 | N26: =SUM(B26:M26) -> 949142.5
A27: TOTAL DE INGRESOS | B27: =B26+B24 -> 197330.96 | C27: =C26+C24 -> 209035.49 | D27: =D26+D24 -> 233825.91 | E27: =E26+E24 -> 238169.83 | F27: =F26+F24 -> 261106.04 | G27: =G26+G24 -> 244196.76 | H27: =H26+H24 -> 255396.76 | I27: =I26+I24 -> 265273.97 | ... M27: =M26+M24 -> 312483.42 | N27: =SUM(B27:M27) -> 3101828.3
A28: SALIDAS DE EFECTIVO
A29: LUZ(BIM) | B29: 0 | C29: 1890 | D29: 0 | E29: 1890 | F29: 0 | G29: 1890 | H29: 0 | I29: 1890 | J29: 0 | K29: 1890 | L29: 0 | M29: 1890 | N29: =SUM(B29:M29) -> 11340
A30: AGUA(BIM) | B30: 262.5 | C30: 336 | D30: 252 | E30: 262.5 | F30: 336 | G30: 262.5 | H30: 252 | I30: 262.5 | J30: 262.5 | K30: 336 | L30: 262.5 | M30: 367.5 | N30: =SUM(B30:M30) -> 3454.5
A31: TELEFONO E INTERNET | B31: 1050 | C31: 366.45 | D31: 366.45 | E31: 366.45 | F31: 366.45 | G31: 366.45 | H31: 366.45 | I31: 366.45 | J31: 366.45 | K31: 366.45 | L31: 366.45 | M31: 366.45 | N31: =SUM(B31:M31) -> 5080.95
A32: RENTA | B32: 9450 | C32: 9450 | D32: 9450 | E32: 9450 | F32: 9450 | G32: 9450 | H32: 9450 | I32: 9450 | J32: 9450 | K32: 9450 | L32: 9450 | M32: 9450 | N32: =SUM(B32:M32) -> 113400
A33: SEGURIDAD | B33: 1682.5 | C33: 0 | D33: 0 | E33: 0 | F33: 0 | G33: 682.5 | H33: 0 | I33: 0 | J33: 0 | K33: 0 | L33: 0 | M33: 682.5 | N33: =SUM(B33:M33) -> 3047.5
A34: SUELDOS | B34: 19950 | C34: 19950 | D34: 19950 | E34: 19950 | F34: 19950 | G34: 19950 | H34: 19950 | I34: 19950 | J34: 19950 | K34: 19950 | L34: 19950 | M34: 19950 | N34: =SUM(B34:M34) -> 239400
A35: BONO PUNTUALIDAD | B35: 1575 | C35: 1575 | D35: 1575 | E35: 1575 | F35: 1575 | G35: 1575 | H35: 1575 | I35: 1575 | J35: 1575 | K35: 1575 | L35: 1575 | M35: 1575 | N35: =SUM(B35:M35) -> 18900
A36: PAGO IMSS | B36: 6300 | C36: 2940 | D36: 6300 | E36: 2940 | F36: 6300 | G36: 2940 | H36: 6300 | I36: 2940 | J36: 6300 | K36: 2940 | L36: 6300 | M36: 2940 | N36: =SUM(B36:M36) -> 55440
A37: LAVANDERIA | B37: 571.2 | C37: 571.2 | D37: 571.2 | E37: 571.2 | F37: 571.2 | G37: 571.2 | H37: 571.2 | I37: 571.2 | J37: 571.2 | K37: 571.2 | L37: 571.2 | M37: 571.2 | N37: =SUM(B37:M37) -> 6854.4
A38: IMPUESTOS | B38: 3285.83 | C38: 3285.83 | D38: 3285.83 | E38: 3285.83 | F38: 3285.83 | G38: 3285.83 | H38: 3285.83 | I38: 3285.83 | J38: 3285.83 | K38: 3285.83 | L38: 3285.83 | M38: 3285.83 | N38: =SUM(B38:M38) -> 39429.96
A39: INSUMOS | B39: 23023.44 | C39: 27035.1 | D39: 31395.6 | E39: 31482.81 | F39: 33139.8 | G39: 22849.02 | H39: 27122.31 | I39: 29215.35 | J39: 32703.75 | K39: 29389.77 | L39: 31046.76 | M39: 31308.39 | N39: =SUM(B39:M39) -> 349712.1
A40: SALDO ANTES DE MINIMO | B40: =B27-B29-B30-B31-B32-B33-B34-B35-B36-B37-B39-B38 -> 130180.49 | C40: =C27-C29-C30-C31-C32-C33-C34-C36-C37-C39-C35-C38 -> 141635.91 | D40: =D27-D29-D30-D31-D32-D33-D34-D36-D37-D39-D35-D38 -> 160679.83 | E40: =E27-E29-E30-E31-E32-E33-E34-E36-E37-E39-E35-E38 -> 166396.04 | F40: =F27-F29-F30-F31-F32-F33-F34-F36-F37-F39-F35-F38 -> 186131.76 | G40: =G27-G29-G30-G31-G32-G33-G34-G36-G37-G39-G35-G38 -> 180374.26 | H40: =H27-H29-H30-H31-H32-H33-H34-H36-H37-H39-H35-H38 -> 186523.97 | I40: =I27-I29-I30-I31-I32-I33-I34-I36-I37-I39-I35-I38 -> 195767.64 | J40: =J27-J29-J30-J31-J32-J33-J34-J36-J37-J39-J35-J38 -> 212757.91 | ... M40: =M27-M29-M30-M31-M32-M33-M34-M36-M37-M39-M35-M38 -> 240096.55 | N40: =SUM(B40:M40) -> 2255768.9
A41: SALDO MINIMO DE OPERACIÓN | B41: 26250 | C41: 26250 | D41: 26250 | E41: 26250 | F41: 26250 | G41: 26250 | H41: 26250 | I41: 26250 | J41: 26250 | K41: 26250 | L41: 26250 | M41: 26250 | N41: =SUM(B41:M41) -> 315000
A42: EFECTIVO NUEVO DISPONIBLE | B42: =B40-B41 -> 103930.49 | C42: =C40-C41 -> 115385.91 | D42: =D40-D41 -> 134429.83 | E42: =E40-E41 -> 140146.04 | F42: =F40-F41 -> 159881.76 | G42: =G40-G41 -> 154124.26 | H42: =H40-H41 -> 160273.97 | I42: =I40-I41 -> 169517.64 | ... M42: =M40-M41 -> 213846.55 | N42: =SUM(B42:M42) -> 1940768.9
A44: 2022
B46: ENE | C46: FEB | D46: MAR | E46: ABR | F46: MAY | G46: JUN | H46: JUL | I46: AGO | J46: SEP | K46: OCT | L46: NOV | M46: DIC | N46: TOTAL
A47: SALDO INICIAL | B47: =M42+M41 -> 240096.55 | C47: =B67+B68 -> 293109.81 | D47: =C68+C67 -> 311426.42 | E47: =D67+D68 -> 336523.44 | F47: =E68+E67 -> 354594.76 | G47: =F67+F68 -> 377201.31 | H47: =G67+G68 -> 384630.99 | I47: =H67+H68 -> 398664.99 | J47: =I67+I68 -> 416668.21 | K47: =J67+J68 -> 440046.03 | L47: =K67+K68 -> 459605.33 | M47: =L67+L68 -> 477548.85 | N47: =SUM(B47:M47) -> 4490116.7
A48: ENTRADAS DE EFECTIVO
A49: VENTA-SERVICIO | B49: =VENTAS!D50 -> 80027.9 | C49: =VENTAS!E50 -> 96416.91 | D49: =VENTAS!F50 -> 110146.82 | E49: =VENTAS!G50 -> 97468 | F49: =VENTAS!H50 -> 105913.15 | G49: =VENTAS!I50 -> 80217.39 | H49: =VENTAS!J50 -> 89926.8 | I49: =VENTAS!K50 -> 89158.6 | ... M49: =VENTAS!O50 -> 96090.1 | N49: =SUM(B49:M49) -> 1145769.1
A50: CAPITAL SEMILLA | B50: 50000 | N50: 50000
A51: TOTAL DE INGRESOS | B51: =B49+B47+B50 -> 370124.45 | C51: =C49+C47 -> 389526.72 | D51: =D49+D47 -> 421573.24 | E51: =E49+E47 -> 433991.44 | F51: =F49+F47 -> 460507.91 | G51: =G49+G47 -> 457418.7 | H51: =H49+H47 -> 474557.79 | I51: =I49+I47 -> 487823.59 | J51: =J49+J47 -> 520986.21 | ... M51: =M49+M47 -> 573638.95 | N51: =N49+N50 -> 1195769.1
A52: SALIDAS DE EFECTIVO
A53: LUZ(BIM) | B53: 0 | C53: 1984.5 | D53: 0 | E53: 1984.5 | F53: 0 | G53: 1984.5 | H53: 0 | I53: 1984.5 | J53: 0 | K53: 1984.5 | L53: 0 | M53: 1984.5 | N53: =SUM(B53:M53) -> 11907
A54: AGUA(BIM) | B54: 275.63 | C54: 352.8 | D54: 264.6 | E54: 275.63 | F54: 352.8 | G54: 275.63 | H54: 264.6 | I54: 275.63 | J54: 275.63 | K54: 352.8 | L54: 275.63 | M54: 385.88 | N54: =SUM(B54:M54) -> 3627.26
A55: TELEFONO E INTERNET | B55: 1102.5 | C55: 384.77 | D55: 384.77 | E55: 384.77 | F55: 384.77 | G55: 384.77 | H55: 384.77 | I55: 384.77 | J55: 384.77 | K55: 384.77 | L55: 384.77 | M55: 384.77 | N55: =SUM(B55:M55) -> 5334.97
A56: RENTA | B56: 9922.5 | C56: 9922.5 | D56: 9922.5 | E56: 9922.5 | F56: 9922.5 | G56: 9922.5 | H56: 9922.5 | I56: 9922.5 | J56: 9922.5 | K56: 9922.5 | L56: 9922.5 | M56: 9922.5 | N56: =SUM(B56:M56) -> 119070
A57: SEGURIDAD | B57: 1766.63 | C57: 0 | D57: 0 | E57: 0 | F57: 0 | G57: 716.63 | H57: 0 | I57: 0 | J57: 0 | K57: 0 | L57: 0 | M57: 716.63 | N57: =SUM(B57:M57) -> 3199.89
A58: SUELDOS | B58: 23152.5 | C58: 23152.5 | D58: 23152.5 | E58: 23152.5 | F58: 23152.5 | G58: 23152.5 | H58: 23152.5 | I58: 23152.5 | J58: 23152.5 | K58: 23152.5 | L58: 23152.5 | M58: 23152.5 | N58: =SUM(B58:M58) -> 277830
A59: BONO PUNTUALIDAD | B59: 1653.75 | C59: 1653.75 | D59: 1653.75 | E59: 1653.75 | F59: 1653.75 | G59: 1653.75 | H59: 1653.75 | I59: 1653.75 | J59: 1653.75 | K59: 1653.75 | L59: 1653.75 | M59: 1653.75 | N59: =SUM(B59:M59) -> 19845
A60: PAGO IMSS | B60: 6615 | C60: 3087 | D60: 6615 | E60: 3087 | F60: 6615 | G60: 3087 | H60: 6615 | I60: 3087 | J60: 6615 | K60: 3087 | L60: 6615 | M60: 3087 | N60: =SUM(B60:M60) -> 58212
A61: LAVANDERIA | B61: 599.76 | C61: 599.76 | D61: 599.76 | E61: 599.76 | F61: 599.76 | G61: 599.76 | H61: 599.76 | I61: 599.76 | J61: 599.76 | K61: 599.76 | L61: 599.76 | M61: 599.76 | N61: =SUM(B61:M61) -> 7197.12
A62: IMPUESTOS | B62: 4390.95 | C62: 4390.95 | D62: 4390.95 | E62: 4390.95 | F62: 4390.95 | G62: 4390.95 | H62: 4390.95 | I62: 4390.95 | J62: 4390.95 | K62: 4390.95 | L62: 4390.95 | M62: 4390.95 | N62: =SUM(B62:M62) -> 52691.4
A63: INSUMOS | B63: 25181.75 | C63: 30218.1 | D63: 35712.3 | E63: 31591.65 | F63: 33880.9 | G63: 24266.05 | H63: 26555.3 | I63: 23350.35 | J63: 31591.65 | K63: 31591.65 | L63: 29760.25 | M63: 30218.1 | N63: =SUM(B63:M63) -> 353918.05
A64: PAGO CAP PRÉSTAMO | B64: 1853.67 | C64: 1872.21 | D64: 1890.93 | E64: 1909.84 | F64: 1928.94 | G64: 1948.23 | H64: 1967.71 | I64: 1987.39 | J64: 2007.26 | K64: 2027.33 | L64: 2047.61 | M64: 2068.08 | N64: =SUM(B64:M64) -> 23509.2
A65: PAG. INTERES PRESTAMO | B65: 500 | C65: 481.46 | D65: 462.74 | E65: 443.83 | F65: 424.73 | G65: 405.44 | H65: 385.96 | I65: 366.28 | J65: 346.41 | K65: 326.34 | L65: 306.06 | M65: 285.59 | N65: =SUM(B65:M65) -> 4734.84
A66: SALDO ANTES DE MINIMO | B66: =B51-B53-B54-B55-B56-B57-B58-B59-B60-B61-B63-B62-B64-B65 -> 293109.81 | C66: =C51-C53-C54-C55-C56-C57-C58-C59-C60-C61-C63-C62-C64-C65 -> 311426.42 | D66: =D51-D53-D54-D55-D56-D57-D58-D59-D60-D61-D63-D62-D64-D65 -> 336523.44 | E66: =E51-E53-E54-E55-E56-E57-E58-E59-E60-E61-E63-E62-E64-E65 -> 354594.76 | F66: =F51-F53-F54-F55-F56-F57-F58-F59-F60-F61-F63-F62-F64-F65 -> 377201.31 | G66: =G51-G53-G54-G55-G56-G57-G58-G59-G60-G61-G63-G62-G64-G65 -> 384630.99 | H66: =H51-H53-H54-H55-H56-H57-H58-H59-H60-H61-H63-H62-H64-H65 -> 398664.99 | I66: =I51-I53-I54-I55-I56-I57-I58-I59-I60-I61-I63-I62-I64-I65 -> 416668.21 | ... M66: =M51-M53-M54-M55-M56-M57-M58-M59-M60-M61-M63-M62-M64-M65 -> 494788.94 | N66: =N51-N53-N54-N55-N56-N57-N58-N59-N60-N61-N62-N63-N64-N65 -> 254692.39
A67: SALDO MINIMO DE OPERACIÓN | B67: 27562.5 | C67: 27562.5 | D67: 27562.5 | E67: 27562.5 | F67: 27562.5 | G67: 27562.5 | H67: 27562.5 | I67: 27562.5 | J67: 27562.5 | K67: 27562.5 | L67: 27562.5 | M67: 27562.5 | N67: =SUM(B67:M67) -> 330750
A68: EFECTIVO NUEVO DISPONIBLE | B68: =B66-B67 -> 265547.31 | C68: =C66-C67 -> 283863.92 | D68: =D66-D67 -> 308960.94 | E68: =E66-E67 -> 327032.26 | F68: =F66-F67 -> 349638.81 | G68: =G66-G67 -> 357068.49 | H68: =H66-H67 -> 371102.49 | I68: =I66-I67 -> 389105.71 | ... M68: =M66-M67 -> 467226.44 | N68: =SUM(B68:M68) -> 4414059.1
A70: 2023
B72: ENE | C72: FEB | D72: MAR | E72: ABR | F72: MAY | G72: JUN | H72: JUL | I72: AGO | J72: SEP | K72: OCT | L72: NOV | M72: DIC | N72: TOTAL
A73: SALDO INICIAL | B73: =M68+M67 -> 494788.94 | C73: =B93+B94 -> 500400.69 | D73: =C94+C93 -> 525253.23 | E73: =D93+D94 -> 554544.02 | F73: =E94+E93 -> 582111.99 | G73: =F93+F94 -> 614122.76 | H73: =G93+G94 -> 622464.62 | I73: =H93+H94 -> 639112.92 | J73: =I93+I94 -> 656217.55 | K73: =J93+J94 -> 687270.99 | L73: =K93+K94 -> 713387.96 | M73: =L93+L94 -> 735065.61 | N73: =SUM(B73:M73) -> 7324741.3
A74: ENTRADAS DE EFECTIVO
A75: VENTA-SERVICIO | B75: =VENTAS!D69 -> 91205.17 | C75: =VENTAS!E69 -> 111806.4 | D75: =VENTAS!F69 -> 123734.01 | E75: =VENTAS!G69 -> 118007.35 | F75: =VENTAS!H69 -> 124142.85 | G75: =VENTAS!I69 -> 90390.45 | H75: =VENTAS!J69 -> 104841.77 | I75: =VENTAS!K69 -> 105131.26 | ... M75: =VENTAS!O69 -> 118501.04 | N75: =SUM(B75:M75) -> 1339491.2
A76: CAPITAL SEMILLA | B76: 0
A77: TOTAL DE INGRESOS | B77: =B75+B73+B76 -> 585994.11 | C77: =C75+C73 -> 612207.09 | D77: =D75+D73 -> 648987.24 | E77: =E75+E73 -> 672551.37 | F77: =F75+F73 -> 706254.84 | G77: =G75+G73 -> 704513.21 | H77: =H75+H73 -> 727306.39 | I77: =I75+I73 -> 744244.18 | J77: =J75+J73 -> 780283.54 | ... M77: =M75+M73 -> 853566.65 | N77: =N75+N76 -> 1339491.2
A78: SALIDAS DE EFECTIVO
A79: LUZ(BIM) | B79: 0 | C79: 2083.73 | D79: 0 | E79: 2083.73 | F79: 0 | G79: 2083.73 | H79: 0 | I79: 2083.73 | J79: 0 | K79: 2083.73 | L79: 0 | M79: 2083.73 | N79: =SUM(B79:M79) -> 12502.38
A80: AGUA(BIM) | B80: 289.41 | C80: 370.44 | D80: 277.83 | E80: 289.41 | F80: 370.44 | G80: 289.41 | H80: 277.83 | I80: 289.41 | J80: 289.41 | K80: 370.44 | L80: 289.41 | M80: 405.17 | N80: =SUM(B80:M80) -> 3808.61
A81: TELEFONO E INTERNET | B81: 1157.63 | C81: 404.01 | D81: 404.01 | E81: 404.01 | F81: 404.01 | G81: 404.01 | H81: 404.01 | I81: 404.01 | J81: 404.01 | K81: 404.01 | L81: 404.01 | M81: 404.01 | N81: =SUM(B81:M81) -> 5601.74
A82: RENTA | B82: 10418.63 | C82: 10418.63 | D82: 10418.63 | E82: 10418.63 | F82: 10418.63 | G82: 10418.63 | H82: 10418.63 | I82: 10418.63 | J82: 10418.63 | K82: 10418.63 | L82: 10418.63 | M82: 10418.63 | N82: =SUM(B82:M82) -> 125023.56
A83: SEGURIDAD | B83: 0 | C83: 0 | D83: 0 | E83: 0 | F83: 0 | G83: 752.46 | H83: 0 | I83: 0 | J83: 0 | K83: 0 | L83: 0 | M83: 752.46 | N83: =SUM(B83:M83) -> 1504.92
A84: SUELDOS | B84: 24310.13 | C84: 24310.13 | D84: 24310.13 | E84: 24310.13 | F84: 24310.13 | G84: 24310.13 | H84: 24310.13 | I84: 24310.13 | J84: 24310.13 | K84: 24310.13 | L84: 24310.13 | M84: 24310.13 | N84: =SUM(B84:M84) -> 291721.56
A85: BONO PUNTUALIDAD | B85: 1736.44 | C85: 1736.44 | D85: 1736.44 | E85: 1736.44 | F85: 1736.44 | G85: 1736.44 | H85: 1736.44 | I85: 1736.44 | J85: 1736.44 | K85: 1736.44 | L85: 1736.44 | M85: 1736.44 | N85: =SUM(B85:M85) -> 20837.28
A86: PAGO IMSS | B86: 6945.75 | C86: 3241.35 | D86: 6945.75 | E86: 3241.35 | F86: 6945.75 | G86: 3241.35 | H86: 6945.75 | I86: 3241.35 | J86: 6945.75 | K86: 3241.35 | L86: 6945.75 | M86: 3241.35 | N86: =SUM(B86:M86) -> 61122.6
A87: LAVANDERIA | B87: 629.75 | C87: 629.75 | D87: 629.75 | E87: 629.75 | F87: 629.75 | G87: 629.75 | H87: 629.75 | I87: 629.75 | J87: 629.75 | K87: 629.75 | L87: 629.75 | M87: 629.75 | N87: =SUM(B87:M87) -> 7557
A88: IMPUESTOS | B88: 8907.01 | C88: 8907.01 | D88: 8907.01 | E88: 8907.01 | F88: 8907.01 | G88: 8907.01 | H88: 8907.01 | I88: 8907.01 | J88: 8907.01 | K88: 8907.01 | L88: 8907.01 | M88: 8907.01 | N88: =SUM(B88:M88) -> 106884.12
A89: INSUMOS | B89: 28845 | C89: 32498.7 | D89: 38460 | E89: 36056.25 | F89: 36056.25 | G89: 26922 | H89: 32210.25 | I89: 33652.5 | J89: 37017.75 | K89: 35575.5 | L89: 33844.8 | M89: 33652.5 | N89: =SUM(B89:M89) -> 404791.5
A90: PAGO CAP PRÉSTAMO | B90: 2088.76 | C90: 2109.65 | D90: 2130.75 | E90: 2152.05 | F90: 2173.57 | G90: 2195.31 | H90: 2217.26 | I90: 2239.44 | J90: 2261.83 | K90: 2284.45 | L90: 2307.29 | M90: 2330.44 | N90: =SUM(B90:M90) -> 26490.8
A91: PAG. INTERES PRESTAMO | B91: 264.91 | C91: 244.02 | D91: 222.92 | E91: 210.62 | F91: 180.1 | G91: 158.36 | H91: 136.41 | I91: 114.23 | J91: 91.84 | K91: 69.22 | L91: 46.38 | M91: 23.3 | N91: =SUM(B91:M91) -> 1762.31
A92: SALDO ANTES DE MINIMO | B92: =B77-B79-B80-B81-B82-B83-B84-B85-B86-B87-B89-B88-B90-B91 -> 500400.69 | C92: =C77-C79-C80-C81-C82-C83-C84-C85-C86-C87-C89-C88-C90-C91 -> 525253.23 | D92: =D77-D79-D80-D81-D82-D83-D84-D85-D86-D87-D89-D88-D90-D91 -> 554544.02 | E92: =E77-E79-E80-E81-E82-E83-E84-E85-E86-E87-E89-E88-E90-E91 -> 582111.99 | F92: =F77-F79-F80-F81-F82-F83-F84-F85-F86-F87-F89-F88-F90-F91 -> 614122.76 | G92: =G77-G79-G80-G81-G82-G83-G84-G85-G86-G87-G89-G88-G90-G91 -> 622464.62 | H92: =H77-H79-H80-H81-H82-H83-H84-H85-H86-H87-H89-H88-H90-H91 -> 639112.92 | I92: =I77-I79-I80-I81-I82-I83-I84-I85-I86-I87-I89-I88-I90-I91 -> 656217.55 | ... M92: =M77-M79-M80-M81-M82-M83-M84-M85-M86-M87-M89-M88-M90-M91 -> 764671.73 | N92: =SUM(B92:M92) -> 7594624.1
A93: SALDO MINIMO DE OPERACIÓN | B93: 28940.63 | C93: 28940.63 | D93: 28940.63 | E93: 28940.63 | F93: 28940.63 | G93: 28940.63 | H93: 28940.63 | I93: 28940.63 | J93: 28940.63 | K93: 28940.63 | L93: 28940.63 | M93: 28940.63 | N93: =SUM(B93:M93) -> 347287.56
A94: EFECTIVO NUEVO DISPONIBLE | B94: =B92-B93 -> 471460.06 | C94: =C92-C93 -> 496312.6 | D94: =D92-D93 -> 525603.39 | E94: =E92-E93 -> 553171.36 | F94: =F92-F93 -> 585182.13 | G94: =G92-G93 -> 593523.99 | H94: =H92-H93 -> 610172.29 | I94: =I92-I93 -> 627276.92 | ... M94: =M92-M93 -> 735731.1 | N94: =SUM(B94:M94) -> 7247336.5
A96: 2024
B98: ENE | C98: FEB | D98: MAR | E98: ABR | F98: MAY | G98: JUN | H98: JUL | I98: AGO | J98: SEP | K98: OCT | L98: NOV | M98: DIC | N98: TOTAL
A99: SALDO INICIAL | B99: =M94+M93 -> 764671.73 | C99: =B119+B120 -> 787227.73 | D99: =C120+C119 -> 831569.18 | E99: =D119+D120 -> 880558.7 | F99: =E120+E119 -> 918161.06 | G99: =F119+F120 -> 961660.02 | H99: =G119+G120 -> 976925.94 | I99: =H119+H120 -> 1010115.5 | J99: =I119+I120 -> 1045168.9 | K99: =J119+J120 -> 1128580.6 | L99: =K119+K120 -> 1175004.7 | M99: =L119+L120 -> 1211817.3 | N99: =SUM(B99:M99) -> 11691461
A100: ENTRADAS DE EFECTIVO
A101: VENTA-SERVICIO | B101: =VENTAS!D88 -> 114764.96 | C101: =VENTAS!E88 -> 138180.88 | D101: =VENTAS!F88 -> 154529.42 | E101: =VENTAS!G88 -> 138423.91 | F101: =VENTAS!H88 -> 144088.07 | G101: =VENTAS!I88 -> 104762.35 | H101: =VENTAS!J88 -> 130652.62 | I101: =VENTAS!K88 -> 130826.94 | ... M101: =VENTAS!O88 -> 137771.45 | N101: =SUM(B101:M101) -> 1628237.4
A102: CAPITAL SEMILLA | B102: 0
A103: TOTAL DE INGRESOS | B103: =B101+B99+B102 -> 879436.69 | C103: =C101+C99 -> 925408.61 | D103: =D101+D99 -> 986098.6 | E103: =E101+E99 -> 1018982.6 | F103: =F101+F99 -> 1062249.1 | G103: =G101+G99 -> 1066422.4 | H103: =H101+H99 -> 1107578.6 | I103: =I101+I99 -> 1140942.4 | J103: =J101+J99 -> 1195767.8 | ... M103: =M101+M99 -> 1349588.8 | N103: =N101+N102 -> 1628237.4
A104: SALIDAS DE EFECTIVO
A105: LUZ(BIM) | B105: 0 | C105: 2187.91 | D105: 0 | E105: 2187.91 | F105: 0 | G105: 2187.91 | H105: 0 | I105: 2187.91 | J105: 0 | K105: 2187.91 | L105: 0 | M105: 2187.91 | N105: =SUM(B105:M105) -> 13127.46
A106: AGUA(BIM) | B106: 303.88 | C106: 388.96 | D106: 291.72 | E106: 303.88 | F106: 388.96 | G106: 303.88 | H106: 291.72 | I106: 303.88 | J106: 303.88 | K106: 388.96 | L106: 303.88 | M106: 425.43 | N106: =SUM(B106:M106) -> 3999.03
A107: TELEFONO E INTERNET | B107: 1215.51 | C107: 424.21 | D107: 424.21 | E107: 424.21 | F107: 424.21 | G107: 424.21 | H107: 424.21 | I107: 424.21 | J107: 424.21 | K107: 424.21 | L107: 424.21 | M107: 424.21 | N107: =SUM(B107:M107) -> 5881.82
A108: RENTA | B108: 10939.56 | C108: 10939.56 | D108: 10939.56 | E108: 10939.56 | F108: 10939.56 | G108: 10939.56 | H108: 10939.56 | I108: 10939.56 | J108: 10939.56 | K108: 10939.56 | L108: 10939.56 | M108: 10939.56 | N108: =SUM(B108:M108) -> 131274.72
...

Sheet Estado de Resultados
B2: 2020 | C2: 2021 | D2: 2022 | E2: 2023 | F2: 2024
A3: VENTAS NETAS | B3: 784650 | C3: 949042.5 | D3: =VENTAS!P51 -> 1142776.6 | E3: =VENTAS!P70 -> 1341393 | F3: =VENTAS!P89 -> 1630321.1
A4: COSTO DE VENTA | B4: 265833 | C4: 349712.1 | D4: 353917.7 | E4: 404791.5 | F4: 431009.2
A5: UTILIDAD BRUTA | B5: =B3-B4 -> 518817 | C5: =C3-C4 -> 599330.4 | D5: =D3-D4 -> 788858.92 | E5: =E3-E4 -> 936601.49 | F5: =F3-F4 -> 1199311.9
A6: GASTOS DE OPERACIÓN | B6: =SUM(B7:B16) -> 420241.6 | C6: =SUM(C7:C16) -> 467601.95 | D6: =SUM(D7:D16) -> 516907.93 | E6: =SUM(E7:E16) -> 540364.09 | F6: =SUM(F7:F16) -> 566847.98
A7: SUELDOS | B7: 228000 | C7: 239400 | D7: 277830 | E7: 291721.56 | F7: 306307.56
A8: IMSS | B8: 46800 | C8: 55440 | D8: 58212 | E8: 61122.6 | F8: 64178.73
A9: RENTA | B9: 108000 | C9: 113400 | D9: 119070 | E9: 125023.5 | F9: 131274.68
A10: DEPRECIACION (10%) | B10: 10684.6 | C10: 10684.6 | D10: 10684.6 | E10: 10684.6 | F10: 10684.6
A11: BONO DE PUNTUALIDAD | B11: 0 | C11: 18900 | D11: 19845 | E11: 20837.25 | F11: 21879.11
A12: LUZ | B12: 10800 | C12: 11340 | D12: 11907 | E12: 12502.35 | F12: 13127.47
A13: AGUA | B13: 3290 | C13: 3454.5 | D13: 3627.33 | E13: 3808.59 | F13: 3999.025
A14: SEGURIDAD | B14: 1300 | C14: 3047.5 | D14: 3199.88 | E14: 1504.91 | F14: 1580.16
A15: TEL/INTERNET | B15: 4839 | C15: 5080.95 | D15: 5335 | E15: 5601.75 | F15: 5881.83
A16: LAVANDERIA | B16: 6528 | C16: 6854.4 | D16: 7197.12 | E16: 7556.98 | F16: 7934.82
A17: UAII | B17: =B5-B6 -> 98575.4 | C17: =C5-C6 -> 131728.45 | D17: =D5-D6 -> 271950.99 | E17: =E5-E6 -> 396237.4 | F17: =F5-F6 -> 632463.94
A18: INTERESES | B18: 0 | C18: 0 | D18: 4734.84 | E18: 1753.31 | F18: 0
A19: UAI | B19: =B17-B18 -> 98575.4 | C19: =C17-C18 -> 131728.45 | D19: =D17-D18 -> 267216.15 | E19: =E17-E18 -> 394484.09 | F19: =F17-F18 -> 632463.94
A20: ISR | B20: 29572.46 | C20: 39518.54 | D20: 80164.52 | E20: 118343.14 | F20: 189712.18
A21: PTU | B21: 9857.49 | C21: 13172.85 | D21: 26721.51 | E21: 39447.71 | F21: 63237.39
A22: UDI | B22: =B19-B20-B21 -> 59145.45 | C22: =C19-C20-C21 -> 79037.06 | D22: =D19-D20-D21 -> 160330.12 | E22: =E19-E20-E21 -> 236693.24 | F22: =F19-F20-F21 -> 379514.37
A23: ACCIONES COMUNES | B23: 3 | C23: 3 | D23: 3 | E23: 3 | F23: 3
A24: UPA | B24: =B22/B23 -> 19715.15 | C24: =C22/C23 -> 26345.687 | D24: =D22/D23 -> 53443.373 | E24: =E22/E23 -> 78897.747 | F24: =F22/F23 -> 126504.79

Sheet Balance
A1: 2020
A2: ACTIVO | D2: PASIVO
A3: CIRCULANTE | B3: =B4+B5 -> 143413.46 | D3: CORTO PLAZO | E3: =E4 -> 39429.944
A4: bancos | B4: ='[1]FLUJO DE EFECTIVO'!M16 -> 137013.46 | D4: impuestos x pagar | E4: ='[1]ESTADO DE RESULTADO'!B18+'[1]ESTADO DE RESULTADO'!B19 -> 39429.944
A5: cuentas x cobrar | B5: 6400
A6: FIJO | B6: =B7+B9+B11+B13-B8-B10-B12-B14 -> 96161.4 | D6: LARGO PLAZO | E6: =E7 -> 0
A7: mob. Y equipo | B7: ='[1]tabla de inversion'!L3 -> 83025
A8: dep acum | B8: =B7*0.1 -> 8302.5 | D8: TOTAL PASIVO | E8: =E3+E6 -> 39429.944
A9: equipo computo | B9: ='[1]tabla de inversion'!L4 -> 3000
A10: dep acum | B10: =B9*0.1 -> 300 | D10: CAPITAL CONTABLE | E10: =E11+E12 -> 209144.92
A11: enseres | B11: ='[1]tabla de inversion'!L5 -> 12732 | D11: capital social | E11: 150000
A12: dep acum | B12: =B11*0.1 -> 1273.2 | D12: utilidad del ejercicio | E12: ='[1]ESTADO DE RESULTADO'!B20 -> 59144.916
A13: ep oficina | B13: ='[1]tabla de inversion'!L6 -> 8089
A14: dep acum | B14: =B13*0.1 -> 808.9 | D14: TOTAL CAPITAL | E14: =E10 -> 209144.92
A15: DIFERIDO | B15: =B16 -> 9000
A16: depositos en garantia | B16: ='[1]FLUJO DE EFECTIVO'!B10/2 -> 9000 | D16: TOTAL CAPITAL + PASIVO | E16: =E14+E8 -> 248574.86
A17: TOTAL ACTIVO | B17: =SUM(B3+B6+B15) -> 248574.86
A19: 2021
A20: ACTIVO | D20: PASIVO
A21: CIRCULANTE | B21: =B22+B23+0.02 -> 246396.57 | D21: CORTO PLAZO | E21: =E22 -> 52691.38
A22: bancos | B22: ='[1]FLUJO DE EFECTIVO'!M37 -> 240096.55 | D22: impuestos x pagar | E22: ='[1]ESTADO DE RESULTADO'!B42+'[1]ESTADO DE RESULTADO'!B43 -> 52691.38
A23: cuentas x cobrar | B23: 6300
A24: FIJO | B24: =B25+B27+B29+B31-B26-B28-B30-B32 -> 85476.8 | D24: LARGO PLAZO | E24: =E25 -> 0
A25: mob. Y equipo | B25: ='[1]tabla de inversion'!L3 -> 83025
A26: dep acum | B26: =(B25*0.1)*2 -> 16605 | D26: TOTAL PASIVO | E26: =E21+E24 -> 52691.38
A27: equipo computo | B27: ='[1]tabla de inversion'!L4 -> 3000
A28: dep acum | B28: =(B27*0.1)*2 -> 600 | D28: CAPITAL CONTABLE | E28: =E29+E30 -> 288181.99
A29: enseres | B29: ='[1]tabla de inversion'!L5 -> 12732 | D29: capital social | E29: 150000
A30: dep acum | B30: =(B29*0.1)*2 -> 2546.4 | D30: utilidad del ejercicio | E30: ='[1]ESTADO DE RESULTADO'!B44+E12 -> 138181.99
A31: ep oficina | B31: ='[1]tabla de inversion'!L6 -> 8089
A32: dep acum | B32: =(B31*0.1)*2 -> 1617.8 | D32: TOTAL CAPITAL | E32: =E28 -> 288181.99
A33: DIFERIDO | B33: =B34 -> 9000
A34: depositos en garantia | B34: 9000 | D34: TOTAL CAPITAL + PASIVO | E34: =E32+E26 -> 340873.37
A35: TOTAL ACTIVO | B35: =SUM(B21+B24+B33) -> 340873.37
A37: 2022
A38: ACTIVO | D38: PASIVO
A39: CIRCULANTE | B39: =B40+B41+0.02 -> 498090.77 | D39: CORTO PLAZO | E39: =E40+E41 -> 133374.87
A40: bancos | B40: ='[1]FLUJO DE EFECTIVO'!M60-6.06 -> 494783.25 | D40: impuestos x pagar | E40: ='[1]ESTADO DE RESULTADO'!B66+'[1]ESTADO DE RESULTADO'!B67-2+0.05 -> 106884.07
A41: cuentas x cobrar | B41: 3307.5 | D41: prestamo | E41: =50000-'[1]FLUJO DE EFECTIVO'!N58 -> 26490.8
A42: FIJO | B42: =B43+B45+B47+B49-B44-B46-B48-B50 -> 74792.2
A43: mob. Y equipo | B43: 83025 | D43: LARGO PLAZO
A44: dep acum | B44: =(B43*0.1)*3 -> 24907.5 | D44: TOTAL PASIVO | E44: =E39+E43 -> 133374.87
A45: equipo computo | B45: 3000 | H45: =(B41+B23)/2 -> 4803.75
A46: dep acum | B46: =(B45*0.1)*3 -> 900 | D46: CAPITAL CONTABLE | E46: =E47+E48 -> 448508.09
A47: enseres | B47: 12732 | D47: capital social | E47: 150000
A48: dep acum | B48: =(B47*0.1)*3 -> 3819.6 | D48: utilidad del ejercicio | E48: ='[1]ESTADO DE RESULTADO'!B68+E30 -> 298508.09
A49: ep oficina | B49: 8089
A50: dep acum | B50: =(B49*0.1)*3 -> 2426.7 | D50: TOTAL CAPITAL | E50: =E46 -> 448508.09
A51: DIFERIDO | B51: =B52 -> 9000
A52: depositos en garantia | B52: 9000 | D52: TOTAL CAPITAL + PASIVO | E52: =E50+E44-0.01 -> 581882.95
A53: TOTAL ACTIVO | B53: =SUM(B39+B42+B51)-0.02 -> 581882.95
A55: 2023
A56: ACTIVO | D56: PASIVO
A57: CIRCULANTE | B57: =B58+B59+0.02 -> 769890.26 | D57: CORTO PLAZO | E57: =E58+E59 -> 157790.86
A58: bancos | B58: ='[1]FLUJO DE EFECTIVO'!M83 -> 764680.92 | D58: impuestos x pagar | E58: ='[1]ESTADO DE RESULTADO'!B90+'[1]ESTADO DE RESULTADO'!B91 -> 157790.86
A59: cuentas x cobrar | B59: ='[1]2023'!N7 -> 5209.32 | D59: prestamo | E59: =E41-'[1]FLUJO DE EFECTIVO'!N81 -> 0
A60: FIJO | B60: =B61+B63+B65+B67-B62-B64-B66-B68 -> 64107.6
A61: mob. Y equipo | B61: 83025 | D61: LARGO PLAZO
A62: dep acum | B62: =(B61*0.1)*4 -> 33210 | D62: TOTAL PASIVO | E62: =E57+E61 -> 157790.86
A63: equipo computo | B63: 3000
A64: dep acum | B64: =(B63*0.1)*4 -> 1200 | D64: CAPITAL CONTABLE | E64: =E65+E66 -> 685194.41
A65: enseres | B65: 12732 | D65: capital social | E65: 150000 | H65: =(B59+B41)/2 -> 4258.41
A66: dep acum | B66: =(B65*0.1)*4 -> 5092.8 | D66: utilidad del ejercicio | E66: =E48+'[1]ESTADO DE RESULTADO'!B92 -> 535194.41
A67: ep oficina | B67: 8089
A68: dep acum | B68: =(B67*0.1)*4 -> 3235.6 | D68: TOTAL CAPITAL | E68: =E64 -> 685194.41
A69: DIFERIDO | B69: =B70 -> 9000
A70: depositos en garantia | B70: 9000 | D70: TOTAL CAPITAL + PASIVO | E70: =E68+E62 -> 842985.27
A71: TOTAL ACTIVO | B71: =SUM(B57+B60+B69)-12.59 -> 842985.27
A73: 2024
A74: ACTIVO | D74: PASIVO
A75: CIRCULANTE | B75: =B76+B77+0.02 -> 1255145.4 | D75: CORTO PLAZO | E75: =E76+E77 -> 252949.58
A76: bancos | B76: ='[1]FLUJO DE EFECTIVO'!M106 -> 1247852.3 | D76: impuestos x pagar | E76: ='[1]ESTADO DE RESULTADO'!B114+'[1]ESTADO DE RESULTADO'!B115 -> 252949.58
A77: cuentas x cobrar | B77: ='[1]2024'!N7 -> 7293.04 | D77: prestamo | E77: 0
A78: FIJO | B78: =B79+B81+B83+B85-B80-B82-B84-B86 -> 53423
A79: mob. Y equipo | B79: 83025 | D79: LARGO PLAZO | H79: =(B77+B59)/2 -> 6251.18
A80: dep acum | B80: =(B79*0.1)*5 -> 41512.5 | D80: TOTAL PASIVO | E80: =E75+E79 -> 252949.58
A81: equipo computo | B81: 3000
A82: dep acum | B82: =(B81*0.1)*5 -> 1500 | D82: CAPITAL CONTABLE | E82: =E83+E84 -> 1064617.1
A83: enseres | B83: 12732 | D83: capital social | E83: 150000
A84: dep acum | B84: =(B83*0.1)*5 -> 6366 | D84: utilidad del ejercicio | E84: =E66+'[1]ESTADO DE RESULTADO'!B116 -> 914617.14
A85: ep oficina | B85: 8089
A86: dep acum | B86: =(B85*0.1)*5 -> 4044.5 | D86: TOTAL CAPITAL | E86: =E82 -> 1064617.1
A87: DIFERIDO | B87: =B88 -> 9000
A88: depositos en garantia | B88: 9000 | D88: TOTAL CAPITAL + PASIVO | E88: =E86+E80-1.47 -> 1317565.2
A89: TOTAL ACTIVO | B89: =SUM(B75+B78+B87)-3.11 -> 1317565.3

Sheet Punto Equilibrio
A1: 2020
A2: Precio Venta | B2: 605.56
A3: Costo Venta | B3: 83.06 | C3: Punto Equilibrio | D3: =B4/(B2-B3) -> 783.84115
A4: Costos Fijos | B4: ='Estado de Resultados'!B6-'Estado de Resultados'!B10 -> 409557
A7: 2021
A8: Precio Venta | B8: 635.83
A9: Costo Venta | B9: 87.21 | C9: Punto Equilibrio | D9: =B10/(B8-B9) -> 813.3731
A10: Costos Fijos | B10: ='Estado de Resultados'!C6-'Estado de Resultados'!C10-'Estado de Resultados'!B10 -> 446232.75
A13: 2022
A14: Precio Venta | B14: 612.41
A15: Costo Venta | B15: 91.57 | C15: Punto Equilibrio | D15: =B16/(B14-B15) -> 971.93635
A16: Costos Fijos | B16: ='Estado de Resultados'!D6-'Estado de Resultados'!D10 -> 506223.33
A19: 2023
A20: Precio Venta | B20: 637.07
A21: Costo Venta | B21: 96.15 | C21: Punto Equilibrio | D21: =B22/(B20-B21) -> 979.21964
A22: Costos Fijos | B22: ='Estado de Resultados'!E6-'Estado de Resultados'!E10 -> 529679.49
A25: 2024
A26: Precio Venta | B26: 668.93
A27: Costo Venta | B27: 100.96 | C27: Punto Equilibrio | D27: =B28/(B26-B27) -> 979.21261
A28: Costos Fijos | B28: ='Estado de Resultados'!F6-'Estado de Resultados'!F10 -> 556163.38

Sheet Razones Financieras
E1: 2020 | F1: 2021 | G1: 2022 | H1: 2023 | I1: 2024
A3: Capital de trabajo | B3: Activo Circulante-Pasivo Corto Plazo | E3: =Balance!B3-Balance!E3 -> 103983.52 | F3: =Balance!B21-Balance!E21 -> 193705.19 | G3: =Balance!B39-Balance!E39 -> 364715.9 | H3: =Balance!B57-Balance!E57 -> 612099.4 | I3: =Balance!B75-Balance!E75 -> 1002195.8
A4: Liquidez | B4: Activo Circulante/Pasivo Corto Plazo | E4: =Balance!B3/Balance!E3 -> 3.6371713 | F4: =Balance!B21/Balance!E21 -> 4.6762216 | G4: =Balance!B39/Balance!E39 -> 3.7345174 | H4: =Balance!B57/Balance!E57 -> 4.8791816 | I4: =Balance!B75/Balance!E75 -> 4.9620378
A7: Rotacion de Clientes | B7: Ventas a credito/Promedio Cuentas por Cobrar | E7: =VENTAS!P8/Balance!B5 -> 14 | F7: =VENTAS!P26/Balance!B23 -> 13.75 | G7: =VENTAS!P44/Balance!H45 -> 13.770492 | H7: =VENTAS!P63/Balance!H65 -> 16.718456 | I7: =VENTAS!P82/Balance!H79 -> 15.16666
A8: Dias cliente | B8: 30 días/Rotacion CxC | E8: =30/E7 -> 2.1428571 | F8: =30/F7 -> 2.1818182 | G8: =30/G7 -> 2.1785714 | H8: =30/H7 -> 1.7944241 | I8: =30/I7 -> 1.9780229
A9: Rotación de Activos | B9: Ventas/Activos Totales | E9: ='Estado de Resultados'!B3/Balance!B17 -> 3.1565944 | F9: ='Estado de Resultados'!C3/Balance!B35 -> 2.7841497 | G9: ='Estado de Resultados'!D3/Balance!B53 -> 1.9639287 | H9: ='Estado de Resultados'!E3/Balance!B71 -> 1.5912413 | I9: ='Estado de Resultados'!F3/Balance!B89 -> 1.2373741
A12: Razon de dependencia financiera | B12: Pasivo total/Activo Total | E12: =Balance!E8/Balance!B17 -> 0.15862402 | F12: =Balance!E26/Balance!B35 -> 0.15457758 | G12: =Balance!E44/Balance!B53 -> 0.22921254 | H12: =Balance!E62/Balance!B71 -> 0.18718104 | I12: =Balance!E80/Balance!B89 -> 0.19198258
A13: Razon Pasivo Capital | B13: Pasivo total/Capital Contable | E13: =Balance!E8/Balance!E14 -> 0.1885293 | F13: =Balance!E26/Balance!E28 -> 0.18284064 | G13: =Balance!E44/Balance!E46 -> 0.29737451 | H13: =Balance!E62/Balance!E64 -> 0.23028626 | I13: =Balance!E80/Balance!E82 -> 0.23759675
A14: Razon Cobertura Interes | B14: UAII/Gastos por interes | E14: ='Estado de Resultados'!B17/0 -> #DIV/0! | F14: ='Estado de Resultados'!C17/'Estado de Resultados'!C18 -> #DIV/0! | G14: ='Estado de Resultados'!D17/'Estado de Resultados'!D18 -> 57.436152 | H14: ='Estado de Resultados'!E17/'Estado de Resultados'!E18 -> 225.99392 | I14: ='Estado de Resultados'!F17/'Estado de Resultados'!F18 -> #DIV/0!
A15: Razon Inversion Propia | B15: Capital contable/Activo Total | E15: =Balance!E10/Balance!B17 -> 0.84137598 | F15: =Balance!E28/Balance!B35 -> 0.84542241 | G15: =Balance!E46/Balance!B53 -> 0.77078747 | H15: =Balance!E64/Balance!B71 -> 0.81281896 | I15: =Balance!E82/Balance!B89 -> 0.80801853
A18: Rendimiento de la inversion | B18: Utilidad Neta Despues Imptos/Activos Totales | E18: ='Estado de Resultados'!B22/Balance!B17 -> 0.23793818 | F18: ='Estado de Resultados'!C22/Balance!B35 -> 0.23186634 | G18: ='Estado de Resultados'!D22/Balance!B53 -> 0.27553672 | H18: ='Estado de Resultados'!E22/Balance!B71 -> 0.28077981 | I18: ='Estado de Resultados'!F22/Balance!B89 -> 0.28804218
A19: Rendimiento del capital | B19: Utilidad Neta Depues Imptos/Capital Social | E19: ='Estado de Resultados'!B22/Balance!E11 -> 0.394303 | F19: ='Estado de Resultados'!C22/Balance!E29 -> 0.52691373 | G19: ='Estado de Resultados'!D22/Balance!E47 -> 1.0688675 | H19: ='Estado de Resultados'!E22/Balance!E65 -> 1.5779549 | I19: ='Estado de Resultados'!F22/Balance!E83 -> 2.5300958
A20: Margen Utilidad | B20: Utilidad Neta Despues Imptos/Ventas Netas | E20: ='Estado de Resultados'!B22/'Estado de Resultados'!B3 -> 0.07537813 | F20: ='Estado de Resultados'!C22/'Estado de Resultados'!C3 -> 0.083280844 | G20: ='Estado de Resultados'!D22/'Estado de Resultados'!D3 -> 0.14029874 | H20: ='Estado de Resultados'!E22/'Estado de Resultados'!E3 -> 0.17645332 | I20: ='Estado de Resultados'!F22/'Estado de Resultados'!F3 -> 0.23278504

Sheet Evaluacion Financiera
A1: PRI | B1: 2020 | C1: 2021 | D1: 2022 | E1: 2023 | F1: 2024
A2: Bancos | B2: =Balance!B4 -> 137013.46 | C2: =Balance!B22 -> 240096.55 | D2: =Balance!B40 -> 494783.25 | E2: =Balance!B58 -> 764680.92 | F2: =Balance!B76 -> 1247852.3 | H2: La inversión regresa en un lapso de 12 meses y 19 días
A3: Inversion | B3: 150000 | G3: =B3-B2 -> 12986.54
G4: =(G3*12)/C2 -> 0.64906589
G5: =G4*30 -> 19.471977 | H5: dias
A7: TCR | B7: 2020 | C7: 2021 | D7: 2022 | E7: 2023 | F7: 2024
A8: Utilidad N | B8: ='Estado de Resultados'!B22 -> 59145.45 | C8: ='Estado de Resultados'!C22 -> 79037.06 | D8: ='Estado de Resultados'!D22 -> 160330.12 | E8: ='Estado de Resultados'!E22 -> 236693.24 | F8: ='Estado de Resultados'!F22 -> 379514.37
A9: Promedio | B9: =AVERAGE(B8:F8) -> 182944.05
A10: Inv Inicial | B10: 150000
A12: TCR | B12: =B9/B10 -> 1.219627
A16: TIR
A17: INV | B17: -150000 | C17: -150000 | E17: TREMA | F17: 0.22
A18: FLUJOS 2020 | B18: =Flujos!M17 -> 137013.46 | C18: =(B18)/(1+$F$17)^1 -> 112306.11
A19: 2021 | B19: =Flujos!M40 -> 240096.55 | C19: =(B19)/(1+$F$17)^2 -> 161311.84
A20: 2022 | B20: =Flujos!M66 -> 494788.94 | C20: =(B20)/(1+$F$17)^3 -> 272483.68
A21: 2023 | B21: =Flujos!M92 -> 764671.73 | C21: =(B21)/(1+$F$17)^4 -> 345172.12
A22: 2024 | B22: =Flujos!M118 -> 1247855.6 | C22: =(B22)/(1+$F$17)^5 -> 461705.63
A23: TIR | B23: =IRR(B17:B22) -> 1.5511231
